{"image_id":"1205","document":"\u99ac\u82f1\u4e5d\/\u96dc\u652f\u652f\u51fa\/\u96dc\u652f\u652f\u51fa.pdf","page_no":"028","url":"http:\/\/pic.pimg.tw\/ronnywang\/1393581098-362766563.jpg","width":"7020","height":"4964","cells":{"1":{"1":{"id":"1205-1-1","x":279,"y":682,"width":337,"height":190},"2":{"id":"1205-1-2","x":279,"y":872,"width":337,"height":177},"3":{"id":"1205-1-3","x":279,"y":1049,"width":337,"height":176},"4":{"id":"1205-1-4","x":279,"y":1225,"width":337,"height":174},"5":{"id":"1205-1-5","x":279,"y":1399,"width":337,"height":176},"6":{"id":"1205-1-6","x":279,"y":1575,"width":337,"height":176},"7":{"id":"1205-1-7","x":279,"y":1751,"width":337,"height":175},"8":{"id":"1205-1-8","x":279,"y":1926,"width":337,"height":175},"9":{"id":"1205-1-9","x":279,"y":2101,"width":337,"height":178},"10":{"id":"1205-1-10","x":279,"y":2279,"width":337,"height":178},"11":{"id":"1205-1-11","x":279,"y":2457,"width":337,"height":174},"12":{"id":"1205-1-12","x":279,"y":2631,"width":337,"height":174},"13":{"id":"1205-1-13","x":279,"y":2805,"width":337,"height":176},"14":{"id":"1205-1-14","x":279,"y":2981,"width":337,"height":175},"15":{"id":"1205-1-15","x":279,"y":3156,"width":337,"height":178},"16":{"id":"1205-1-16","x":279,"y":3334,"width":337,"height":174},"17":{"id":"1205-1-17","x":279,"y":3508,"width":337,"height":174},"18":{"id":"1205-1-18","x":279,"y":3682,"width":337,"height":175},"19":{"id":"1205-1-19","x":279,"y":3857,"width":337,"height":175},"20":{"id":"1205-1-20","x":279,"y":4032,"width":337,"height":174},"21":{"id":"1205-1-21","x":279,"y":4206,"width":337,"height":175},"22":{"id":"1205-1-22","x":279,"y":4381,"width":337,"height":528}},"2":{"1":{"id":"1205-2-1","x":616,"y":682,"width":575,"height":190},"2":{"id":"1205-2-2","x":616,"y":872,"width":575,"height":177},"3":{"id":"1205-2-3","x":616,"y":1049,"width":575,"height":176},"4":{"id":"1205-2-4","x":616,"y":1225,"width":575,"height":174},"5":{"id":"1205-2-5","x":616,"y":1399,"width":575,"height":176},"6":{"id":"1205-2-6","x":616,"y":1575,"width":575,"height":176},"7":{"id":"1205-2-7","x":616,"y":1751,"width":575,"height":175},"8":{"id":"1205-2-8","x":616,"y":1926,"width":576,"height":175},"9":{"id":"1205-2-9","x":616,"y":2101,"width":576,"height":178},"10":{"id":"1205-2-10","x":616,"y":2279,"width":576,"height":178},"11":{"id":"1205-2-11","x":616,"y":2457,"width":576,"height":174},"12":{"id":"1205-2-12","x":616,"y":2631,"width":576,"height":174},"13":{"id":"1205-2-13","x":616,"y":2805,"width":576,"height":176},"14":{"id":"1205-2-14","x":616,"y":2981,"width":576,"height":175},"15":{"id":"1205-2-15","x":616,"y":3156,"width":576,"height":178},"16":{"id":"1205-2-16","x":616,"y":3334,"width":576,"height":174},"17":{"id":"1205-2-17","x":616,"y":3508,"width":576,"height":174},"18":{"id":"1205-2-18","x":616,"y":3682,"width":576,"height":175},"19":{"id":"1205-2-19","x":616,"y":3857,"width":576,"height":175},"20":{"id":"1205-2-20","x":616,"y":4032,"width":576,"height":174},"21":{"id":"1205-2-21","x":616,"y":4206,"width":576,"height":175},"22":{"id":"1205-2-22","x":616,"y":4381,"width":576,"height":528}},"3":{"1":{"id":"1205-3-1","x":1191,"y":682,"width":4758,"height":190},"2":{"id":"1205-3-2","x":1191,"y":872,"width":4758,"height":177},"3":{"id":"1205-3-3","x":1191,"y":1049,"width":4758,"height":176},"4":{"id":"1205-3-4","x":1191,"y":1225,"width":4758,"height":174},"5":{"id":"1205-3-5","x":1191,"y":1399,"width":4758,"height":176},"6":{"id":"1205-3-6","x":1191,"y":1575,"width":4758,"height":176},"7":{"id":"1205-3-7","x":1191,"y":1751,"width":4758,"height":175},"8":{"id":"1205-3-8","x":1191,"y":1926,"width":4758,"height":175},"9":{"id":"1205-3-9","x":1192,"y":2101,"width":4757,"height":178},"10":{"id":"1205-3-10","x":1192,"y":2279,"width":4757,"height":178},"11":{"id":"1205-3-11","x":1192,"y":2457,"width":4757,"height":174},"12":{"id":"1205-3-12","x":1192,"y":2631,"width":4757,"height":174},"13":{"id":"1205-3-13","x":1192,"y":2805,"width":4757,"height":176},"14":{"id":"1205-3-14","x":1192,"y":2981,"width":4757,"height":175},"15":{"id":"1205-3-15","x":1192,"y":3156,"width":4757,"height":178},"16":{"id":"1205-3-16","x":1192,"y":3334,"width":4757,"height":174},"17":{"id":"1205-3-17","x":1192,"y":3508,"width":4757,"height":174},"18":{"id":"1205-3-18","x":1192,"y":3682,"width":4757,"height":175},"19":{"id":"1205-3-19","x":1192,"y":3857,"width":4757,"height":175},"20":{"id":"1205-3-20","x":1192,"y":4032,"width":4757,"height":174},"21":{"id":"1205-3-21","x":1192,"y":4206,"width":4757,"height":175},"22":{"id":"1205-3-22","x":1192,"y":4381,"width":4757,"height":528}},"4":{"1":{"id":"1205-4-1","x":5949,"y":682,"width":742,"height":190},"2":{"id":"1205-4-2","x":5949,"y":872,"width":742,"height":177},"3":{"id":"1205-4-3","x":5949,"y":1049,"width":742,"height":176},"4":{"id":"1205-4-4","x":5949,"y":1225,"width":742,"height":174},"5":{"id":"1205-4-5","x":5949,"y":1399,"width":742,"height":176},"6":{"id":"1205-4-6","x":5949,"y":1575,"width":742,"height":176},"7":{"id":"1205-4-7","x":5949,"y":1751,"width":742,"height":175},"8":{"id":"1205-4-8","x":5949,"y":1926,"width":742,"height":175},"9":{"id":"1205-4-9","x":5949,"y":2101,"width":742,"height":178},"10":{"id":"1205-4-10","x":5949,"y":2279,"width":742,"height":178},"11":{"id":"1205-4-11","x":5949,"y":2457,"width":742,"height":174},"12":{"id":"1205-4-12","x":5949,"y":2631,"width":742,"height":174},"13":{"id":"1205-4-13","x":5949,"y":2805,"width":742,"height":176},"14":{"id":"1205-4-14","x":5949,"y":2981,"width":742,"height":175},"15":{"id":"1205-4-15","x":5949,"y":3156,"width":742,"height":178},"16":{"id":"1205-4-16","x":5949,"y":3334,"width":742,"height":174},"17":{"id":"1205-4-17","x":5949,"y":3508,"width":742,"height":174},"18":{"id":"1205-4-18","x":5949,"y":3682,"width":742,"height":175},"19":{"id":"1205-4-19","x":5949,"y":3857,"width":742,"height":175},"20":{"id":"1205-4-20","x":5949,"y":4032,"width":742,"height":174},"21":{"id":"1205-4-21","x":5949,"y":4206,"width":742,"height":175},"22":{"id":"1205-4-22","x":5949,"y":4381,"width":742,"height":528}}}}