{"image_id":"136","document":"\u5433\u80b2\u6607\/\u500b\u4eba\u6350\u8d08\u6536\u5165\/\u5433\u80b2\u6607\u500b\u4eba\u6350\u8d08\u6536\u5165.pdf","page_no":"0014","url":"img_orig\/c9003e695a6914fd942ca288f04b2285-0014.jpg","width":"3514","height":"2488","cells":{"1":{"1":{"id":"136-1-1","x":170,"y":368,"width":167,"height":97},"2":{"id":"136-2-1","x":170,"y":465,"width":167,"height":86},"3":{"id":"136-3-1","x":170,"y":551,"width":167,"height":88},"4":{"id":"136-4-1","x":170,"y":639,"width":167,"height":88},"5":{"id":"136-5-1","x":170,"y":727,"width":167,"height":88},"6":{"id":"136-6-1","x":170,"y":815,"width":167,"height":88},"7":{"id":"136-7-1","x":170,"y":903,"width":167,"height":86},"8":{"id":"136-8-1","x":170,"y":989,"width":167,"height":88},"9":{"id":"136-9-1","x":170,"y":1077,"width":167,"height":87},"10":{"id":"136-10-1","x":170,"y":1164,"width":167,"height":88},"11":{"id":"136-11-1","x":170,"y":1252,"width":169,"height":88},"12":{"id":"136-12-1","x":170,"y":1340,"width":169,"height":86},"13":{"id":"136-13-1","x":170,"y":1426,"width":169,"height":88},"14":{"id":"136-14-1","x":170,"y":1514,"width":169,"height":88},"15":{"id":"136-15-1","x":170,"y":1602,"width":169,"height":89},"16":{"id":"136-16-1","x":170,"y":1691,"width":169,"height":88},"17":{"id":"136-17-1","x":170,"y":1779,"width":169,"height":88},"18":{"id":"136-18-1","x":170,"y":1867,"width":169,"height":88},"19":{"id":"136-19-1","x":170,"y":1955,"width":169,"height":86},"20":{"id":"136-20-1","x":170,"y":2041,"width":169,"height":88},"21":{"id":"136-21-1","x":170,"y":2129,"width":169,"height":88}},"2":{"1":{"id":"136-1-2","x":337,"y":368,"width":286,"height":97},"2":{"id":"136-2-2","x":337,"y":465,"width":288,"height":86},"3":{"id":"136-3-2","x":337,"y":551,"width":288,"height":88},"4":{"id":"136-4-2","x":337,"y":639,"width":288,"height":88},"5":{"id":"136-5-2","x":337,"y":727,"width":288,"height":88},"6":{"id":"136-6-2","x":337,"y":815,"width":288,"height":88},"7":{"id":"136-7-2","x":337,"y":903,"width":288,"height":86},"8":{"id":"136-8-2","x":337,"y":989,"width":288,"height":88},"9":{"id":"136-9-2","x":337,"y":1077,"width":288,"height":87},"10":{"id":"136-10-2","x":337,"y":1164,"width":288,"height":88},"11":{"id":"136-11-2","x":337,"y":1252,"width":290,"height":88},"12":{"id":"136-12-2","x":339,"y":1340,"width":288,"height":86},"13":{"id":"136-13-2","x":339,"y":1426,"width":288,"height":88},"14":{"id":"136-14-2","x":339,"y":1514,"width":288,"height":88},"15":{"id":"136-15-2","x":339,"y":1602,"width":288,"height":89},"16":{"id":"136-16-2","x":339,"y":1691,"width":288,"height":88},"17":{"id":"136-17-2","x":339,"y":1779,"width":288,"height":88},"18":{"id":"136-18-2","x":339,"y":1867,"width":288,"height":88},"19":{"id":"136-19-2","x":339,"y":1955,"width":288,"height":86},"20":{"id":"136-20-2","x":339,"y":2041,"width":290,"height":88},"21":{"id":"136-21-2","x":339,"y":2129,"width":290,"height":88}},"3":{"1":{"id":"136-1-3","x":623,"y":368,"width":434,"height":97},"2":{"id":"136-2-3","x":623,"y":465,"width":434,"height":86},"3":{"id":"136-3-3","x":625,"y":551,"width":432,"height":88},"4":{"id":"136-4-3","x":625,"y":639,"width":432,"height":88},"5":{"id":"136-5-3","x":625,"y":727,"width":434,"height":88},"6":{"id":"136-6-3","x":625,"y":815,"width":434,"height":88},"7":{"id":"136-7-3","x":625,"y":903,"width":434,"height":86},"8":{"id":"136-8-3","x":625,"y":989,"width":434,"height":88},"9":{"id":"136-9-3","x":625,"y":1077,"width":434,"height":87},"10":{"id":"136-10-3","x":625,"y":1164,"width":434,"height":88},"11":{"id":"136-11-3","x":625,"y":1252,"width":434,"height":88},"12":{"id":"136-12-3","x":627,"y":1340,"width":432,"height":88},"13":{"id":"136-13-3","x":627,"y":1426,"width":432,"height":90},"14":{"id":"136-14-3","x":627,"y":1514,"width":432,"height":90},"15":{"id":"136-15-3","x":627,"y":1602,"width":432,"height":89},"16":{"id":"136-16-3","x":627,"y":1691,"width":432,"height":88},"17":{"id":"136-17-3","x":627,"y":1779,"width":434,"height":88},"18":{"id":"136-18-3","x":627,"y":1867,"width":434,"height":88},"19":{"id":"136-19-3","x":627,"y":1955,"width":434,"height":86},"20":{"id":"136-20-3","x":627,"y":2041,"width":434,"height":88},"21":{"id":"136-21-3","x":629,"y":2129,"width":432,"height":88}},"4":{"1":{"id":"136-1-4","x":1057,"y":368,"width":931,"height":97},"2":{"id":"136-2-4","x":1057,"y":465,"width":931,"height":88},"3":{"id":"136-3-4","x":1057,"y":551,"width":931,"height":90},"4":{"id":"136-4-4","x":1057,"y":639,"width":931,"height":90},"5":{"id":"136-5-4","x":1057,"y":727,"width":931,"height":90},"6":{"id":"136-6-4","x":1059,"y":815,"width":929,"height":89},"7":{"id":"136-7-4","x":1059,"y":903,"width":929,"height":87},"8":{"id":"136-8-4","x":1059,"y":989,"width":929,"height":89},"9":{"id":"136-9-4","x":1059,"y":1077,"width":929,"height":89},"10":{"id":"136-10-4","x":1059,"y":1164,"width":929,"height":90},"11":{"id":"136-11-4","x":1059,"y":1252,"width":931,"height":90},"12":{"id":"136-12-4","x":1059,"y":1340,"width":931,"height":90},"13":{"id":"136-13-4","x":1059,"y":1428,"width":931,"height":90},"14":{"id":"136-14-4","x":1059,"y":1516,"width":931,"height":89},"15":{"id":"136-15-4","x":1059,"y":1604,"width":931,"height":89},"16":{"id":"136-16-4","x":1059,"y":1691,"width":931,"height":88},"17":{"id":"136-17-4","x":1059,"y":1779,"width":931,"height":88},"18":{"id":"136-18-4","x":1061,"y":1867,"width":929,"height":88},"19":{"id":"136-19-4","x":1061,"y":1955,"width":929,"height":88},"20":{"id":"136-20-4","x":1061,"y":2041,"width":929,"height":88},"21":{"id":"136-21-4","x":1061,"y":2129,"width":929,"height":90}},"5":{"1":{"id":"136-1-5","x":1988,"y":370,"width":340,"height":95},"2":{"id":"136-2-5","x":1988,"y":465,"width":340,"height":88},"3":{"id":"136-3-5","x":1988,"y":553,"width":340,"height":88},"4":{"id":"136-4-5","x":1988,"y":641,"width":340,"height":88},"5":{"id":"136-5-5","x":1988,"y":729,"width":340,"height":88},"6":{"id":"136-6-5","x":1988,"y":817,"width":340,"height":87},"7":{"id":"136-7-5","x":1988,"y":904,"width":340,"height":86},"8":{"id":"136-8-5","x":1988,"y":990,"width":340,"height":88},"9":{"id":"136-9-5","x":1988,"y":1078,"width":340,"height":88},"10":{"id":"136-10-5","x":1988,"y":1166,"width":340,"height":88},"11":{"id":"136-11-5","x":1988,"y":1254,"width":340,"height":88},"12":{"id":"136-12-5","x":1990,"y":1342,"width":338,"height":88},"13":{"id":"136-13-5","x":1990,"y":1430,"width":338,"height":88},"14":{"id":"136-14-5","x":1990,"y":1518,"width":338,"height":87},"15":{"id":"136-15-5","x":1990,"y":1605,"width":338,"height":88},"16":{"id":"136-16-5","x":1990,"y":1693,"width":338,"height":86},"17":{"id":"136-17-5","x":1990,"y":1779,"width":338,"height":88},"18":{"id":"136-18-5","x":1990,"y":1867,"width":338,"height":88},"19":{"id":"136-19-5","x":1990,"y":1955,"width":338,"height":88},"20":{"id":"136-20-5","x":1990,"y":2043,"width":338,"height":86},"21":{"id":"136-21-5","x":1990,"y":2129,"width":338,"height":90}},"6":{"1":{"id":"136-1-6","x":2328,"y":370,"width":238,"height":95},"2":{"id":"136-2-6","x":2328,"y":465,"width":238,"height":88},"3":{"id":"136-3-6","x":2328,"y":553,"width":238,"height":88},"4":{"id":"136-4-6","x":2328,"y":641,"width":238,"height":88},"5":{"id":"136-5-6","x":2328,"y":729,"width":238,"height":88},"6":{"id":"136-6-6","x":2328,"y":817,"width":238,"height":87},"7":{"id":"136-7-6","x":2328,"y":904,"width":238,"height":86},"8":{"id":"136-8-6","x":2328,"y":990,"width":238,"height":88},"9":{"id":"136-9-6","x":2328,"y":1078,"width":238,"height":88},"10":{"id":"136-10-6","x":2328,"y":1166,"width":238,"height":88},"11":{"id":"136-11-6","x":2328,"y":1254,"width":238,"height":88},"12":{"id":"136-12-6","x":2328,"y":1342,"width":238,"height":88},"13":{"id":"136-13-6","x":2328,"y":1430,"width":238,"height":88},"14":{"id":"136-14-6","x":2328,"y":1518,"width":238,"height":87},"15":{"id":"136-15-6","x":2328,"y":1605,"width":238,"height":88},"16":{"id":"136-16-6","x":2328,"y":1693,"width":238,"height":86},"17":{"id":"136-17-6","x":2328,"y":1779,"width":238,"height":88},"18":{"id":"136-18-6","x":2328,"y":1867,"width":238,"height":88},"19":{"id":"136-19-6","x":2328,"y":1955,"width":238,"height":88},"20":{"id":"136-20-6","x":2328,"y":2043,"width":238,"height":86},"21":{"id":"136-21-6","x":2328,"y":2129,"width":238,"height":90}},"7":{"1":{"id":"136-1-7","x":2566,"y":370,"width":243,"height":95},"2":{"id":"136-2-7","x":2566,"y":465,"width":243,"height":88},"3":{"id":"136-3-7","x":2566,"y":553,"width":243,"height":88},"4":{"id":"136-4-7","x":2566,"y":641,"width":243,"height":88},"5":{"id":"136-5-7","x":2566,"y":729,"width":243,"height":88},"6":{"id":"136-6-7","x":2566,"y":817,"width":243,"height":87},"7":{"id":"136-7-7","x":2566,"y":904,"width":243,"height":86},"8":{"id":"136-8-7","x":2566,"y":990,"width":243,"height":88},"9":{"id":"136-9-7","x":2566,"y":1078,"width":243,"height":88},"10":{"id":"136-10-7","x":2566,"y":1166,"width":243,"height":88},"11":{"id":"136-11-7","x":2566,"y":1254,"width":241,"height":88},"12":{"id":"136-12-7","x":2566,"y":1342,"width":241,"height":89},"13":{"id":"136-13-7","x":2566,"y":1430,"width":241,"height":89},"14":{"id":"136-14-7","x":2566,"y":1518,"width":241,"height":89},"15":{"id":"136-15-7","x":2566,"y":1605,"width":241,"height":88},"16":{"id":"136-16-7","x":2566,"y":1693,"width":241,"height":86},"17":{"id":"136-17-7","x":2566,"y":1779,"width":241,"height":88},"18":{"id":"136-18-7","x":2566,"y":1867,"width":241,"height":88},"19":{"id":"136-19-7","x":2566,"y":1955,"width":241,"height":88},"20":{"id":"136-20-7","x":2566,"y":2043,"width":241,"height":86},"21":{"id":"136-21-7","x":2566,"y":2129,"width":241,"height":90}},"8":{"1":{"id":"136-1-8","x":2809,"y":370,"width":195,"height":95},"2":{"id":"136-2-8","x":2809,"y":465,"width":195,"height":88},"3":{"id":"136-3-8","x":2809,"y":553,"width":195,"height":88},"4":{"id":"136-4-8","x":2809,"y":641,"width":195,"height":88},"5":{"id":"136-5-8","x":2809,"y":729,"width":195,"height":88},"6":{"id":"136-6-8","x":2809,"y":817,"width":195,"height":87},"7":{"id":"136-7-8","x":2809,"y":904,"width":195,"height":86},"8":{"id":"136-8-8","x":2809,"y":990,"width":195,"height":88},"9":{"id":"136-9-8","x":2809,"y":1078,"width":195,"height":88},"10":{"id":"136-10-8","x":2809,"y":1166,"width":195,"height":88},"11":{"id":"136-11-8","x":2809,"y":1254,"width":193,"height":88},"12":{"id":"136-12-8","x":2807,"y":1342,"width":195,"height":89},"13":{"id":"136-13-8","x":2807,"y":1431,"width":195,"height":88},"14":{"id":"136-14-8","x":2807,"y":1519,"width":195,"height":88},"15":{"id":"136-15-8","x":2807,"y":1607,"width":195,"height":86},"16":{"id":"136-16-8","x":2807,"y":1693,"width":195,"height":86},"17":{"id":"136-17-8","x":2807,"y":1779,"width":195,"height":88},"18":{"id":"136-18-8","x":2807,"y":1867,"width":195,"height":88},"19":{"id":"136-19-8","x":2807,"y":1955,"width":195,"height":88},"20":{"id":"136-20-8","x":2807,"y":2043,"width":195,"height":86},"21":{"id":"136-21-8","x":2807,"y":2129,"width":195,"height":90}},"9":{"1":{"id":"136-1-9","x":3004,"y":370,"width":369,"height":95},"2":{"id":"136-2-9","x":3004,"y":465,"width":369,"height":88},"3":{"id":"136-3-9","x":3004,"y":553,"width":369,"height":88},"4":{"id":"136-4-9","x":3004,"y":641,"width":369,"height":88},"5":{"id":"136-5-9","x":3004,"y":729,"width":369,"height":88},"6":{"id":"136-6-9","x":3004,"y":817,"width":369,"height":87},"7":{"id":"136-7-9","x":3004,"y":904,"width":369,"height":86},"8":{"id":"136-8-9","x":3004,"y":990,"width":369,"height":88},"9":{"id":"136-9-9","x":3004,"y":1078,"width":369,"height":88},"10":{"id":"136-10-9","x":3004,"y":1166,"width":369,"height":88},"11":{"id":"136-11-9","x":3004,"y":1254,"width":369,"height":88},"12":{"id":"136-12-9","x":3002,"y":1342,"width":371,"height":89},"13":{"id":"136-13-9","x":3002,"y":1431,"width":371,"height":88},"14":{"id":"136-14-9","x":3002,"y":1519,"width":371,"height":88},"15":{"id":"136-15-9","x":3002,"y":1607,"width":371,"height":86},"16":{"id":"136-16-9","x":3002,"y":1693,"width":371,"height":86},"17":{"id":"136-17-9","x":3002,"y":1779,"width":371,"height":88},"18":{"id":"136-18-9","x":3002,"y":1867,"width":371,"height":88},"19":{"id":"136-19-9","x":3002,"y":1955,"width":371,"height":88},"20":{"id":"136-20-9","x":3002,"y":2043,"width":371,"height":86},"21":{"id":"136-21-9","x":3002,"y":2129,"width":371,"height":90}}},"cellCount":189}