{"image_id":"1442","document":"\u99ac\u82f1\u4e5d\/\u500b\u4eba\u6350\u8d08\u6536\u5165\/\u8299\u4e38-\u500b\u4eba\u6350\u8d08\u6536\u51651.pdf","page_no":"043","url":"http:\/\/pic.pimg.tw\/ronnywang\/1393598689-2025025078.jpg","width":"7020","height":"4964","cells":{"1":{"1":{"id":"1442-1-1","x":294,"y":530,"width":737,"height":179},"2":{"id":"1442-1-2","x":294,"y":709,"width":737,"height":172},"3":{"id":"1442-1-3","x":294,"y":881,"width":737,"height":175},"4":{"id":"1442-1-4","x":294,"y":1056,"width":737,"height":172},"5":{"id":"1442-1-5","x":294,"y":1228,"width":737,"height":179},"6":{"id":"1442-1-6","x":294,"y":1404,"width":737,"height":175},"7":{"id":"1442-1-7","x":294,"y":1579,"width":737,"height":176},"8":{"id":"1442-1-8","x":294,"y":1751,"width":737,"height":179},"9":{"id":"1442-1-9","x":294,"y":1930,"width":737,"height":172},"10":{"id":"1442-1-10","x":294,"y":2102,"width":737,"height":175},"11":{"id":"1442-1-11","x":294,"y":2277,"width":737,"height":176},"12":{"id":"1442-1-12","x":291,"y":2453,"width":740,"height":175},"13":{"id":"1442-1-13","x":291,"y":2628,"width":740,"height":176},"14":{"id":"1442-1-14","x":291,"y":2804,"width":740,"height":175},"15":{"id":"1442-1-15","x":291,"y":2976,"width":740,"height":175},"16":{"id":"1442-1-16","x":291,"y":3151,"width":740,"height":176},"17":{"id":"1442-1-17","x":291,"y":3323,"width":740,"height":179},"18":{"id":"1442-1-18","x":291,"y":3499,"width":740,"height":179},"19":{"id":"1442-1-19","x":291,"y":3678,"width":740,"height":172},"20":{"id":"1442-1-20","x":291,"y":3846,"width":740,"height":176},"21":{"id":"1442-1-21","x":291,"y":4022,"width":740,"height":193}},"2":{"1":{"id":"1442-2-1","x":1031,"y":530,"width":390,"height":179},"2":{"id":"1442-2-2","x":1031,"y":709,"width":390,"height":172},"3":{"id":"1442-2-3","x":1031,"y":881,"width":390,"height":175},"4":{"id":"1442-2-4","x":1031,"y":1056,"width":390,"height":172},"5":{"id":"1442-2-5","x":1031,"y":1228,"width":390,"height":179},"6":{"id":"1442-2-6","x":1031,"y":1407,"width":390,"height":172},"7":{"id":"1442-2-7","x":1031,"y":1579,"width":390,"height":176},"8":{"id":"1442-2-8","x":1031,"y":1755,"width":390,"height":175},"9":{"id":"1442-2-9","x":1031,"y":1930,"width":390,"height":172},"10":{"id":"1442-2-10","x":1031,"y":2102,"width":390,"height":175},"11":{"id":"1442-2-11","x":1031,"y":2277,"width":390,"height":176},"12":{"id":"1442-2-12","x":1031,"y":2453,"width":390,"height":175},"13":{"id":"1442-2-13","x":1031,"y":2628,"width":390,"height":176},"14":{"id":"1442-2-14","x":1031,"y":2804,"width":390,"height":175},"15":{"id":"1442-2-15","x":1031,"y":2979,"width":390,"height":172},"16":{"id":"1442-2-16","x":1031,"y":3151,"width":390,"height":176},"17":{"id":"1442-2-17","x":1031,"y":3327,"width":390,"height":175},"18":{"id":"1442-2-18","x":1031,"y":3502,"width":390,"height":176},"19":{"id":"1442-2-19","x":1031,"y":3678,"width":390,"height":172},"20":{"id":"1442-2-20","x":1031,"y":3850,"width":390,"height":172},"21":{"id":"1442-2-21","x":1031,"y":4022,"width":390,"height":193}},"3":{"1":{"id":"1442-3-1","x":1421,"y":530,"width":481,"height":182},"2":{"id":"1442-3-2","x":1421,"y":709,"width":481,"height":175},"3":{"id":"1442-3-3","x":1421,"y":881,"width":481,"height":179},"4":{"id":"1442-3-4","x":1421,"y":1056,"width":481,"height":176},"5":{"id":"1442-3-5","x":1421,"y":1228,"width":481,"height":179},"6":{"id":"1442-3-6","x":1421,"y":1407,"width":481,"height":176},"7":{"id":"1442-3-7","x":1421,"y":1579,"width":481,"height":176},"8":{"id":"1442-3-8","x":1421,"y":1755,"width":481,"height":179},"9":{"id":"1442-3-9","x":1421,"y":1930,"width":481,"height":176},"10":{"id":"1442-3-10","x":1421,"y":2102,"width":481,"height":179},"11":{"id":"1442-3-11","x":1421,"y":2277,"width":481,"height":180},"12":{"id":"1442-3-12","x":1421,"y":2453,"width":481,"height":179},"13":{"id":"1442-3-13","x":1421,"y":2628,"width":481,"height":180},"14":{"id":"1442-3-14","x":1421,"y":2804,"width":481,"height":175},"15":{"id":"1442-3-15","x":1421,"y":2979,"width":481,"height":176},"16":{"id":"1442-3-16","x":1421,"y":3151,"width":481,"height":176},"17":{"id":"1442-3-17","x":1421,"y":3327,"width":481,"height":175},"18":{"id":"1442-3-18","x":1421,"y":3502,"width":481,"height":179},"19":{"id":"1442-3-19","x":1421,"y":3678,"width":481,"height":172},"20":{"id":"1442-3-20","x":1421,"y":3850,"width":481,"height":175},"21":{"id":"1442-3-21","x":1421,"y":4022,"width":481,"height":197}},"4":{"1":{"id":"1442-4-1","x":1902,"y":533,"width":477,"height":179},"2":{"id":"1442-4-2","x":1902,"y":712,"width":477,"height":172},"3":{"id":"1442-4-3","x":1902,"y":884,"width":477,"height":176},"4":{"id":"1442-4-4","x":1902,"y":1060,"width":477,"height":172},"5":{"id":"1442-4-5","x":1902,"y":1232,"width":477,"height":175},"6":{"id":"1442-4-6","x":1902,"y":1407,"width":477,"height":176},"7":{"id":"1442-4-7","x":1902,"y":1583,"width":477,"height":172},"8":{"id":"1442-4-8","x":1902,"y":1755,"width":477,"height":179},"9":{"id":"1442-4-9","x":1902,"y":1934,"width":477,"height":172},"10":{"id":"1442-4-10","x":1902,"y":2106,"width":477,"height":175},"11":{"id":"1442-4-11","x":1902,"y":2281,"width":477,"height":176},"12":{"id":"1442-4-12","x":1902,"y":2457,"width":477,"height":175},"13":{"id":"1442-4-13","x":1902,"y":2632,"width":477,"height":176},"14":{"id":"1442-4-14","x":1902,"y":2808,"width":477,"height":171},"15":{"id":"1442-4-15","x":1902,"y":2979,"width":477,"height":176},"16":{"id":"1442-4-16","x":1902,"y":3155,"width":477,"height":172},"17":{"id":"1442-4-17","x":1902,"y":3327,"width":477,"height":175},"18":{"id":"1442-4-18","x":1902,"y":3502,"width":477,"height":179},"19":{"id":"1442-4-19","x":1902,"y":3681,"width":477,"height":169},"20":{"id":"1442-4-20","x":1902,"y":3850,"width":477,"height":175},"21":{"id":"1442-4-21","x":1902,"y":4025,"width":477,"height":194}},"5":{"1":{"id":"1442-5-1","x":2379,"y":533,"width":678,"height":179},"2":{"id":"1442-5-2","x":2379,"y":712,"width":678,"height":172},"3":{"id":"1442-5-3","x":2379,"y":884,"width":678,"height":176},"4":{"id":"1442-5-4","x":2379,"y":1060,"width":678,"height":172},"5":{"id":"1442-5-5","x":2379,"y":1232,"width":678,"height":179},"6":{"id":"1442-5-6","x":2379,"y":1407,"width":678,"height":176},"7":{"id":"1442-5-7","x":2379,"y":1583,"width":678,"height":175},"8":{"id":"1442-5-8","x":2379,"y":1755,"width":678,"height":179},"9":{"id":"1442-5-9","x":2379,"y":1934,"width":678,"height":172},"10":{"id":"1442-5-10","x":2379,"y":2106,"width":678,"height":175},"11":{"id":"1442-5-11","x":2379,"y":2281,"width":678,"height":176},"12":{"id":"1442-5-12","x":2379,"y":2457,"width":678,"height":175},"13":{"id":"1442-5-13","x":2379,"y":2632,"width":678,"height":176},"14":{"id":"1442-5-14","x":2379,"y":2808,"width":678,"height":175},"15":{"id":"1442-5-15","x":2379,"y":2979,"width":678,"height":176},"16":{"id":"1442-5-16","x":2379,"y":3155,"width":678,"height":175},"17":{"id":"1442-5-17","x":2379,"y":3327,"width":678,"height":179},"18":{"id":"1442-5-18","x":2379,"y":3502,"width":678,"height":179},"19":{"id":"1442-5-19","x":2379,"y":3681,"width":678,"height":172},"20":{"id":"1442-5-20","x":2379,"y":3850,"width":678,"height":175},"21":{"id":"1442-5-21","x":2379,"y":4025,"width":678,"height":194}},"6":{"1":{"id":"1442-6-1","x":3057,"y":533,"width":1857,"height":183},"2":{"id":"1442-6-2","x":3057,"y":712,"width":1857,"height":176},"3":{"id":"1442-6-3","x":3057,"y":884,"width":1857,"height":179},"4":{"id":"1442-6-4","x":3057,"y":1060,"width":1857,"height":175},"5":{"id":"1442-6-5","x":3057,"y":1232,"width":1857,"height":182},"6":{"id":"1442-6-6","x":3057,"y":1411,"width":1857,"height":175},"7":{"id":"1442-6-7","x":3057,"y":1583,"width":1857,"height":179},"8":{"id":"1442-6-8","x":3057,"y":1758,"width":1857,"height":179},"9":{"id":"1442-6-9","x":3057,"y":1934,"width":1857,"height":175},"10":{"id":"1442-6-10","x":3057,"y":2106,"width":1857,"height":179},"11":{"id":"1442-6-11","x":3057,"y":2281,"width":1860,"height":179},"12":{"id":"1442-6-12","x":3057,"y":2457,"width":1860,"height":179},"13":{"id":"1442-6-13","x":3057,"y":2632,"width":1860,"height":179},"14":{"id":"1442-6-14","x":3057,"y":2808,"width":1860,"height":179},"15":{"id":"1442-6-15","x":3057,"y":2983,"width":1860,"height":176},"16":{"id":"1442-6-16","x":3057,"y":3155,"width":1860,"height":179},"17":{"id":"1442-6-17","x":3057,"y":3330,"width":1860,"height":180},"18":{"id":"1442-6-18","x":3057,"y":3506,"width":1860,"height":179},"19":{"id":"1442-6-19","x":3057,"y":3681,"width":1860,"height":176},"20":{"id":"1442-6-20","x":3057,"y":3853,"width":1860,"height":176},"21":{"id":"1442-6-21","x":3057,"y":4025,"width":1860,"height":197}},"7":{"1":{"id":"1442-7-1","x":4914,"y":537,"width":866,"height":182},"2":{"id":"1442-7-2","x":4914,"y":716,"width":866,"height":175},"3":{"id":"1442-7-3","x":4914,"y":888,"width":866,"height":179},"4":{"id":"1442-7-4","x":4914,"y":1063,"width":866,"height":176},"5":{"id":"1442-7-5","x":4914,"y":1235,"width":866,"height":179},"6":{"id":"1442-7-6","x":4914,"y":1414,"width":866,"height":176},"7":{"id":"1442-7-7","x":4914,"y":1586,"width":866,"height":176},"8":{"id":"1442-7-8","x":4914,"y":1762,"width":866,"height":179},"9":{"id":"1442-7-9","x":4914,"y":1937,"width":866,"height":176},"10":{"id":"1442-7-10","x":4914,"y":2109,"width":866,"height":179},"11":{"id":"1442-7-11","x":4914,"y":2285,"width":866,"height":179},"12":{"id":"1442-7-12","x":4917,"y":2460,"width":863,"height":179},"13":{"id":"1442-7-13","x":4917,"y":2636,"width":863,"height":179},"14":{"id":"1442-7-14","x":4917,"y":2811,"width":863,"height":176},"15":{"id":"1442-7-15","x":4917,"y":2987,"width":863,"height":175},"16":{"id":"1442-7-16","x":4917,"y":3159,"width":863,"height":175},"17":{"id":"1442-7-17","x":4917,"y":3334,"width":863,"height":176},"18":{"id":"1442-7-18","x":4917,"y":3510,"width":863,"height":179},"19":{"id":"1442-7-19","x":4917,"y":3685,"width":863,"height":172},"20":{"id":"1442-7-20","x":4917,"y":3857,"width":863,"height":175},"21":{"id":"1442-7-21","x":4917,"y":4029,"width":863,"height":197}},"8":{"1":{"id":"1442-8-1","x":5780,"y":540,"width":576,"height":179},"2":{"id":"1442-8-2","x":5780,"y":719,"width":576,"height":172},"3":{"id":"1442-8-3","x":5780,"y":891,"width":576,"height":176},"4":{"id":"1442-8-4","x":5780,"y":1067,"width":576,"height":172},"5":{"id":"1442-8-5","x":5780,"y":1239,"width":576,"height":175},"6":{"id":"1442-8-6","x":5780,"y":1414,"width":576,"height":176},"7":{"id":"1442-8-7","x":5780,"y":1590,"width":576,"height":172},"8":{"id":"1442-8-8","x":5780,"y":1762,"width":576,"height":179},"9":{"id":"1442-8-9","x":5780,"y":1941,"width":576,"height":172},"10":{"id":"1442-8-10","x":5780,"y":2113,"width":576,"height":175},"11":{"id":"1442-8-11","x":5780,"y":2288,"width":576,"height":176},"12":{"id":"1442-8-12","x":5780,"y":2464,"width":576,"height":175},"13":{"id":"1442-8-13","x":5780,"y":2639,"width":576,"height":176},"14":{"id":"1442-8-14","x":5780,"y":2815,"width":576,"height":172},"15":{"id":"1442-8-15","x":5780,"y":2987,"width":576,"height":175},"16":{"id":"1442-8-16","x":5780,"y":3162,"width":576,"height":172},"17":{"id":"1442-8-17","x":5780,"y":3334,"width":576,"height":176},"18":{"id":"1442-8-18","x":5780,"y":3510,"width":576,"height":179},"19":{"id":"1442-8-19","x":5780,"y":3689,"width":576,"height":168},"20":{"id":"1442-8-20","x":5780,"y":3857,"width":576,"height":175},"21":{"id":"1442-8-21","x":5780,"y":4032,"width":576,"height":194}},"9":{"1":{"id":"1442-9-1","x":6356,"y":540,"width":330,"height":179},"2":{"id":"1442-9-2","x":6356,"y":719,"width":334,"height":172},"3":{"id":"1442-9-3","x":6356,"y":891,"width":334,"height":176},"4":{"id":"1442-9-4","x":6356,"y":1067,"width":334,"height":172},"5":{"id":"1442-9-5","x":6356,"y":1239,"width":334,"height":179},"6":{"id":"1442-9-6","x":6356,"y":1414,"width":334,"height":176},"7":{"id":"1442-9-7","x":6356,"y":1590,"width":334,"height":175},"8":{"id":"1442-9-8","x":6356,"y":1762,"width":334,"height":179},"9":{"id":"1442-9-9","x":6356,"y":1941,"width":334,"height":172},"10":{"id":"1442-9-10","x":6356,"y":2113,"width":334,"height":175},"11":{"id":"1442-9-11","x":6356,"y":2288,"width":337,"height":176},"12":{"id":"1442-9-12","x":6356,"y":2464,"width":337,"height":175},"13":{"id":"1442-9-13","x":6356,"y":2639,"width":337,"height":176},"14":{"id":"1442-9-14","x":6356,"y":2815,"width":337,"height":175},"15":{"id":"1442-9-15","x":6356,"y":2987,"width":337,"height":175},"16":{"id":"1442-9-16","x":6356,"y":3162,"width":337,"height":176},"17":{"id":"1442-9-17","x":6356,"y":3334,"width":337,"height":179},"18":{"id":"1442-9-18","x":6356,"y":3510,"width":337,"height":179},"19":{"id":"1442-9-19","x":6356,"y":3689,"width":337,"height":171},"20":{"id":"1442-9-20","x":6356,"y":3857,"width":341,"height":175},"21":{"id":"1442-9-21","x":6356,"y":4032,"width":341,"height":194}}}}