{"image_id":"1750","document":"\u99ac\u82f1\u4e5d\/\u500b\u4eba\u6350\u8d08\u6536\u5165\/\u8299\u4e38-\u500b\u4eba\u6350\u8d08\u6536\u51652.pdf","page_no":"0259","url":"img_orig\/c8907700ebc1735b9870145486fed816-0259.jpg","width":"3510","height":"2482","cells":{"1":{"1":{"id":"1750-1-1","x":157,"y":377,"width":172,"height":95},"2":{"id":"1750-2-1","x":159,"y":472,"width":170,"height":87},"3":{"id":"1750-3-1","x":159,"y":559,"width":170,"height":90},"4":{"id":"1750-4-1","x":159,"y":649,"width":170,"height":89},"5":{"id":"1750-5-1","x":159,"y":740,"width":172,"height":86},"6":{"id":"1750-6-1","x":161,"y":826,"width":170,"height":88},"7":{"id":"1750-7-1","x":161,"y":914,"width":170,"height":86},"8":{"id":"1750-8-1","x":161,"y":1002,"width":170,"height":87},"9":{"id":"1750-9-1","x":161,"y":1089,"width":170,"height":86},"10":{"id":"1750-10-1","x":163,"y":1177,"width":168,"height":88},"11":{"id":"1750-11-1","x":163,"y":1265,"width":168,"height":89},"12":{"id":"1750-12-1","x":163,"y":1354,"width":168,"height":86},"13":{"id":"1750-13-1","x":163,"y":1440,"width":168,"height":88},"14":{"id":"1750-14-1","x":164,"y":1528,"width":167,"height":88},"15":{"id":"1750-15-1","x":164,"y":1616,"width":167,"height":89},"16":{"id":"1750-16-1","x":164,"y":1705,"width":167,"height":86},"17":{"id":"1750-17-1","x":164,"y":1793,"width":169,"height":86},"18":{"id":"1750-18-1","x":166,"y":1879,"width":167,"height":86},"19":{"id":"1750-19-1","x":166,"y":1965,"width":167,"height":90},"20":{"id":"1750-20-1","x":166,"y":2055,"width":167,"height":87},"21":{"id":"1750-21-1","x":168,"y":2144,"width":165,"height":88}},"2":{"1":{"id":"1750-1-2","x":329,"y":377,"width":290,"height":95},"2":{"id":"1750-2-2","x":329,"y":472,"width":290,"height":87},"3":{"id":"1750-3-2","x":329,"y":559,"width":290,"height":90},"4":{"id":"1750-4-2","x":329,"y":649,"width":290,"height":89},"5":{"id":"1750-5-2","x":329,"y":738,"width":290,"height":88},"6":{"id":"1750-6-2","x":331,"y":826,"width":288,"height":88},"7":{"id":"1750-7-2","x":331,"y":914,"width":288,"height":86},"8":{"id":"1750-8-2","x":331,"y":1000,"width":288,"height":89},"9":{"id":"1750-9-2","x":331,"y":1089,"width":288,"height":86},"10":{"id":"1750-10-2","x":331,"y":1175,"width":288,"height":90},"11":{"id":"1750-11-2","x":331,"y":1265,"width":290,"height":89},"12":{"id":"1750-12-2","x":331,"y":1354,"width":290,"height":86},"13":{"id":"1750-13-2","x":331,"y":1440,"width":290,"height":88},"14":{"id":"1750-14-2","x":331,"y":1528,"width":290,"height":88},"15":{"id":"1750-15-2","x":331,"y":1616,"width":290,"height":89},"16":{"id":"1750-16-2","x":331,"y":1705,"width":290,"height":86},"17":{"id":"1750-17-2","x":331,"y":1791,"width":290,"height":88},"18":{"id":"1750-18-2","x":333,"y":1879,"width":288,"height":86},"19":{"id":"1750-19-2","x":333,"y":1965,"width":288,"height":90},"20":{"id":"1750-20-2","x":333,"y":2055,"width":288,"height":87},"21":{"id":"1750-21-2","x":333,"y":2142,"width":288,"height":90}},"3":{"1":{"id":"1750-1-3","x":619,"y":377,"width":434,"height":95},"2":{"id":"1750-2-3","x":619,"y":472,"width":434,"height":87},"3":{"id":"1750-3-3","x":619,"y":559,"width":434,"height":90},"4":{"id":"1750-4-3","x":619,"y":649,"width":434,"height":89},"5":{"id":"1750-5-3","x":619,"y":738,"width":434,"height":86},"6":{"id":"1750-6-3","x":619,"y":826,"width":434,"height":86},"7":{"id":"1750-7-3","x":619,"y":914,"width":434,"height":86},"8":{"id":"1750-8-3","x":619,"y":1000,"width":434,"height":88},"9":{"id":"1750-9-3","x":619,"y":1089,"width":434,"height":86},"10":{"id":"1750-10-3","x":619,"y":1175,"width":434,"height":88},"11":{"id":"1750-11-3","x":619,"y":1265,"width":435,"height":88},"12":{"id":"1750-12-3","x":621,"y":1354,"width":433,"height":85},"13":{"id":"1750-13-3","x":621,"y":1440,"width":433,"height":86},"14":{"id":"1750-14-3","x":621,"y":1528,"width":433,"height":86},"15":{"id":"1750-15-3","x":621,"y":1616,"width":433,"height":88},"16":{"id":"1750-16-3","x":621,"y":1705,"width":433,"height":86},"17":{"id":"1750-17-3","x":621,"y":1791,"width":433,"height":86},"18":{"id":"1750-18-3","x":621,"y":1879,"width":433,"height":84},"19":{"id":"1750-19-3","x":621,"y":1965,"width":433,"height":88},"20":{"id":"1750-20-3","x":621,"y":2055,"width":433,"height":87},"21":{"id":"1750-21-3","x":621,"y":2142,"width":433,"height":88}},"4":{"1":{"id":"1750-1-4","x":1053,"y":377,"width":930,"height":96},"2":{"id":"1750-2-4","x":1053,"y":472,"width":930,"height":89},"3":{"id":"1750-3-4","x":1053,"y":559,"width":930,"height":90},"4":{"id":"1750-4-4","x":1053,"y":649,"width":931,"height":88},"5":{"id":"1750-5-4","x":1053,"y":738,"width":931,"height":85},"6":{"id":"1750-6-4","x":1053,"y":824,"width":931,"height":86},"7":{"id":"1750-7-4","x":1053,"y":912,"width":931,"height":86},"8":{"id":"1750-8-4","x":1053,"y":1000,"width":931,"height":86},"9":{"id":"1750-9-4","x":1053,"y":1088,"width":931,"height":86},"10":{"id":"1750-10-4","x":1053,"y":1175,"width":931,"height":86},"11":{"id":"1750-11-4","x":1053,"y":1263,"width":933,"height":88},"12":{"id":"1750-12-4","x":1054,"y":1353,"width":932,"height":84},"13":{"id":"1750-13-4","x":1054,"y":1439,"width":932,"height":86},"14":{"id":"1750-14-4","x":1054,"y":1526,"width":932,"height":86},"15":{"id":"1750-15-4","x":1054,"y":1614,"width":932,"height":88},"16":{"id":"1750-16-4","x":1054,"y":1704,"width":932,"height":86},"17":{"id":"1750-17-4","x":1054,"y":1791,"width":932,"height":85},"18":{"id":"1750-18-4","x":1054,"y":1877,"width":934,"height":85},"19":{"id":"1750-19-4","x":1054,"y":1963,"width":934,"height":88},"20":{"id":"1750-20-4","x":1054,"y":2053,"width":934,"height":88},"21":{"id":"1750-21-4","x":1054,"y":2142,"width":934,"height":86}},"5":{"1":{"id":"1750-1-5","x":1983,"y":377,"width":342,"height":96},"2":{"id":"1750-2-5","x":1983,"y":473,"width":342,"height":88},"3":{"id":"1750-3-5","x":1983,"y":561,"width":342,"height":88},"4":{"id":"1750-4-5","x":1983,"y":649,"width":342,"height":86},"5":{"id":"1750-5-5","x":1984,"y":737,"width":341,"height":86},"6":{"id":"1750-6-5","x":1984,"y":823,"width":341,"height":87},"7":{"id":"1750-7-5","x":1984,"y":910,"width":341,"height":86},"8":{"id":"1750-8-5","x":1984,"y":998,"width":341,"height":88},"9":{"id":"1750-9-5","x":1984,"y":1086,"width":341,"height":86},"10":{"id":"1750-10-5","x":1984,"y":1174,"width":341,"height":87},"11":{"id":"1750-11-5","x":1984,"y":1261,"width":343,"height":90},"12":{"id":"1750-12-5","x":1986,"y":1351,"width":341,"height":86},"13":{"id":"1750-13-5","x":1986,"y":1437,"width":341,"height":88},"14":{"id":"1750-14-5","x":1986,"y":1525,"width":341,"height":87},"15":{"id":"1750-15-5","x":1986,"y":1612,"width":341,"height":90},"16":{"id":"1750-16-5","x":1986,"y":1702,"width":341,"height":86},"17":{"id":"1750-17-5","x":1986,"y":1790,"width":341,"height":86},"18":{"id":"1750-18-5","x":1986,"y":1876,"width":341,"height":86},"19":{"id":"1750-19-5","x":1988,"y":1962,"width":339,"height":89},"20":{"id":"1750-20-5","x":1988,"y":2051,"width":339,"height":88},"21":{"id":"1750-21-5","x":1988,"y":2141,"width":339,"height":87}},"6":{"1":{"id":"1750-1-6","x":2325,"y":377,"width":239,"height":96},"2":{"id":"1750-2-6","x":2325,"y":473,"width":239,"height":88},"3":{"id":"1750-3-6","x":2325,"y":561,"width":239,"height":88},"4":{"id":"1750-4-6","x":2325,"y":649,"width":239,"height":86},"5":{"id":"1750-5-6","x":2325,"y":735,"width":239,"height":88},"6":{"id":"1750-6-6","x":2325,"y":823,"width":239,"height":87},"7":{"id":"1750-7-6","x":2325,"y":910,"width":239,"height":86},"8":{"id":"1750-8-6","x":2325,"y":996,"width":239,"height":90},"9":{"id":"1750-9-6","x":2325,"y":1086,"width":239,"height":86},"10":{"id":"1750-10-6","x":2325,"y":1172,"width":239,"height":89},"11":{"id":"1750-11-6","x":2325,"y":1261,"width":239,"height":90},"12":{"id":"1750-12-6","x":2327,"y":1351,"width":237,"height":86},"13":{"id":"1750-13-6","x":2327,"y":1437,"width":237,"height":88},"14":{"id":"1750-14-6","x":2327,"y":1525,"width":237,"height":87},"15":{"id":"1750-15-6","x":2327,"y":1612,"width":237,"height":90},"16":{"id":"1750-16-6","x":2327,"y":1702,"width":237,"height":86},"17":{"id":"1750-17-6","x":2327,"y":1788,"width":237,"height":88},"18":{"id":"1750-18-6","x":2327,"y":1876,"width":237,"height":86},"19":{"id":"1750-19-6","x":2327,"y":1962,"width":237,"height":89},"20":{"id":"1750-20-6","x":2327,"y":2051,"width":237,"height":88},"21":{"id":"1750-21-6","x":2327,"y":2139,"width":237,"height":89}},"7":{"1":{"id":"1750-1-7","x":2564,"y":377,"width":240,"height":96},"2":{"id":"1750-2-7","x":2564,"y":473,"width":240,"height":88},"3":{"id":"1750-3-7","x":2564,"y":561,"width":240,"height":88},"4":{"id":"1750-4-7","x":2564,"y":649,"width":240,"height":86},"5":{"id":"1750-5-7","x":2564,"y":735,"width":242,"height":86},"6":{"id":"1750-6-7","x":2564,"y":823,"width":242,"height":86},"7":{"id":"1750-7-7","x":2564,"y":910,"width":242,"height":86},"8":{"id":"1750-8-7","x":2564,"y":996,"width":242,"height":88},"9":{"id":"1750-9-7","x":2564,"y":1086,"width":242,"height":86},"10":{"id":"1750-10-7","x":2564,"y":1172,"width":242,"height":88},"11":{"id":"1750-11-7","x":2564,"y":1261,"width":242,"height":88},"12":{"id":"1750-12-7","x":2564,"y":1351,"width":242,"height":84},"13":{"id":"1750-13-7","x":2564,"y":1437,"width":242,"height":86},"14":{"id":"1750-14-7","x":2564,"y":1525,"width":242,"height":86},"15":{"id":"1750-15-7","x":2564,"y":1612,"width":242,"height":88},"16":{"id":"1750-16-7","x":2564,"y":1702,"width":242,"height":86},"17":{"id":"1750-17-7","x":2564,"y":1788,"width":244,"height":86},"18":{"id":"1750-18-7","x":2564,"y":1876,"width":244,"height":84},"19":{"id":"1750-19-7","x":2564,"y":1962,"width":244,"height":87},"20":{"id":"1750-20-7","x":2564,"y":2051,"width":244,"height":88},"21":{"id":"1750-21-7","x":2564,"y":2139,"width":244,"height":88}},"8":{"1":{"id":"1750-1-8","x":2804,"y":377,"width":197,"height":96},"2":{"id":"1750-2-8","x":2804,"y":473,"width":197,"height":88},"3":{"id":"1750-3-8","x":2804,"y":561,"width":197,"height":88},"4":{"id":"1750-4-8","x":2804,"y":649,"width":197,"height":86},"5":{"id":"1750-5-8","x":2804,"y":735,"width":197,"height":86},"6":{"id":"1750-6-8","x":2806,"y":821,"width":195,"height":88},"7":{"id":"1750-7-8","x":2806,"y":909,"width":195,"height":87},"8":{"id":"1750-8-8","x":2806,"y":996,"width":195,"height":88},"9":{"id":"1750-9-8","x":2806,"y":1084,"width":195,"height":88},"10":{"id":"1750-10-8","x":2806,"y":1172,"width":195,"height":88},"11":{"id":"1750-11-8","x":2806,"y":1260,"width":195,"height":89},"12":{"id":"1750-12-8","x":2806,"y":1349,"width":195,"height":86},"13":{"id":"1750-13-8","x":2806,"y":1435,"width":195,"height":88},"14":{"id":"1750-14-8","x":2806,"y":1523,"width":195,"height":88},"15":{"id":"1750-15-8","x":2806,"y":1611,"width":195,"height":89},"16":{"id":"1750-16-8","x":2806,"y":1700,"width":195,"height":88},"17":{"id":"1750-17-8","x":2806,"y":1788,"width":195,"height":86},"18":{"id":"1750-18-8","x":2808,"y":1874,"width":193,"height":86},"19":{"id":"1750-19-8","x":2808,"y":1960,"width":193,"height":89},"20":{"id":"1750-20-8","x":2808,"y":2049,"width":193,"height":90},"21":{"id":"1750-21-8","x":2808,"y":2139,"width":193,"height":88}},"9":{"1":{"id":"1750-1-9","x":3001,"y":377,"width":368,"height":96},"2":{"id":"1750-2-9","x":3001,"y":473,"width":370,"height":88},"3":{"id":"1750-3-9","x":3001,"y":561,"width":370,"height":88},"4":{"id":"1750-4-9","x":3001,"y":649,"width":370,"height":84},"5":{"id":"1750-5-9","x":3001,"y":735,"width":370,"height":86},"6":{"id":"1750-6-9","x":3001,"y":821,"width":370,"height":88},"7":{"id":"1750-7-9","x":3001,"y":909,"width":370,"height":86},"8":{"id":"1750-8-9","x":3001,"y":996,"width":370,"height":88},"9":{"id":"1750-9-9","x":3001,"y":1084,"width":370,"height":86},"10":{"id":"1750-10-9","x":3001,"y":1172,"width":370,"height":88},"11":{"id":"1750-11-9","x":3001,"y":1260,"width":372,"height":89},"12":{"id":"1750-12-9","x":3001,"y":1349,"width":372,"height":86},"13":{"id":"1750-13-9","x":3001,"y":1435,"width":372,"height":88},"14":{"id":"1750-14-9","x":3001,"y":1523,"width":372,"height":88},"15":{"id":"1750-15-9","x":3001,"y":1611,"width":372,"height":89},"16":{"id":"1750-16-9","x":3001,"y":1700,"width":372,"height":86},"17":{"id":"1750-17-9","x":3001,"y":1788,"width":372,"height":86},"18":{"id":"1750-18-9","x":3001,"y":1874,"width":372,"height":86},"19":{"id":"1750-19-9","x":3001,"y":1960,"width":372,"height":89},"20":{"id":"1750-20-9","x":3001,"y":2049,"width":373,"height":88},"21":{"id":"1750-21-9","x":3001,"y":2139,"width":373,"height":88}}},"cellCount":189}