{"image_id":"2078","document":"\u99ac\u82f1\u4e5d\/\u533f\u540d\u6350\u653f\/\u533f\u540d\u6350\u8d08 (2).pdf","page_no":"0118","url":"img_orig\/0b451ff8dd080663662a8d1315320ea7-0118.jpg","width":"3525","height":"2502","cells":{"1":{"1":{"id":"2078-1-1","x":130,"y":380,"width":166,"height":97},"2":{"id":"2078-2-1","x":130,"y":477,"width":166,"height":85},"3":{"id":"2078-3-1","x":130,"y":562,"width":167,"height":88},"4":{"id":"2078-4-1","x":130,"y":650,"width":167,"height":86},"5":{"id":"2078-5-1","x":130,"y":736,"width":167,"height":90},"6":{"id":"2078-6-1","x":132,"y":826,"width":165,"height":86},"7":{"id":"2078-7-1","x":132,"y":912,"width":167,"height":90},"8":{"id":"2078-8-1","x":132,"y":1002,"width":167,"height":87},"9":{"id":"2078-9-1","x":132,"y":1089,"width":167,"height":86},"10":{"id":"2078-10-1","x":132,"y":1175,"width":167,"height":86},"11":{"id":"2078-11-1","x":132,"y":1261,"width":169,"height":89},"12":{"id":"2078-12-1","x":133,"y":1350,"width":168,"height":88},"13":{"id":"2078-13-1","x":133,"y":1436,"width":168,"height":90},"14":{"id":"2078-14-1","x":133,"y":1526,"width":168,"height":88},"15":{"id":"2078-15-1","x":133,"y":1614,"width":170,"height":86},"16":{"id":"2078-16-1","x":133,"y":1700,"width":170,"height":87},"17":{"id":"2078-17-1","x":133,"y":1787,"width":170,"height":88},"18":{"id":"2078-18-1","x":135,"y":1875,"width":168,"height":88},"19":{"id":"2078-19-1","x":135,"y":1963,"width":169,"height":90},"20":{"id":"2078-20-1","x":135,"y":2055,"width":169,"height":88},"21":{"id":"2078-21-1","x":135,"y":2143,"width":169,"height":88}},"2":{"1":{"id":"2078-1-2","x":296,"y":380,"width":289,"height":97},"2":{"id":"2078-2-2","x":296,"y":477,"width":289,"height":85},"3":{"id":"2078-3-2","x":296,"y":562,"width":289,"height":88},"4":{"id":"2078-4-2","x":297,"y":650,"width":288,"height":86},"5":{"id":"2078-5-2","x":297,"y":736,"width":289,"height":90},"6":{"id":"2078-6-2","x":297,"y":826,"width":289,"height":86},"7":{"id":"2078-7-2","x":297,"y":912,"width":289,"height":90},"8":{"id":"2078-8-2","x":299,"y":1002,"width":287,"height":87},"9":{"id":"2078-9-2","x":299,"y":1089,"width":287,"height":86},"10":{"id":"2078-10-2","x":299,"y":1175,"width":287,"height":86},"11":{"id":"2078-11-2","x":299,"y":1261,"width":289,"height":89},"12":{"id":"2078-12-2","x":301,"y":1350,"width":287,"height":88},"13":{"id":"2078-13-2","x":301,"y":1438,"width":287,"height":88},"14":{"id":"2078-14-2","x":301,"y":1526,"width":287,"height":88},"15":{"id":"2078-15-2","x":301,"y":1614,"width":287,"height":86},"16":{"id":"2078-16-2","x":303,"y":1700,"width":285,"height":87},"17":{"id":"2078-17-2","x":303,"y":1787,"width":287,"height":88},"18":{"id":"2078-18-2","x":303,"y":1875,"width":287,"height":88},"19":{"id":"2078-19-2","x":303,"y":1963,"width":287,"height":90},"20":{"id":"2078-20-2","x":304,"y":2053,"width":286,"height":90},"21":{"id":"2078-21-2","x":304,"y":2143,"width":286,"height":88}},"3":{"1":{"id":"2078-1-3","x":585,"y":380,"width":433,"height":97},"2":{"id":"2078-2-3","x":585,"y":477,"width":433,"height":85},"3":{"id":"2078-3-3","x":585,"y":562,"width":433,"height":88},"4":{"id":"2078-4-3","x":585,"y":650,"width":433,"height":86},"5":{"id":"2078-5-3","x":585,"y":736,"width":435,"height":90},"6":{"id":"2078-6-3","x":586,"y":826,"width":434,"height":86},"7":{"id":"2078-7-3","x":586,"y":912,"width":434,"height":90},"8":{"id":"2078-8-3","x":586,"y":1002,"width":434,"height":87},"9":{"id":"2078-9-3","x":586,"y":1089,"width":434,"height":86},"10":{"id":"2078-10-3","x":586,"y":1175,"width":434,"height":86},"11":{"id":"2078-11-3","x":586,"y":1261,"width":436,"height":89},"12":{"id":"2078-12-3","x":588,"y":1350,"width":434,"height":88},"13":{"id":"2078-13-3","x":588,"y":1438,"width":434,"height":90},"14":{"id":"2078-14-3","x":588,"y":1526,"width":434,"height":90},"15":{"id":"2078-15-3","x":588,"y":1614,"width":434,"height":88},"16":{"id":"2078-16-3","x":588,"y":1700,"width":434,"height":88},"17":{"id":"2078-17-3","x":588,"y":1787,"width":436,"height":88},"18":{"id":"2078-18-3","x":590,"y":1875,"width":434,"height":88},"19":{"id":"2078-19-3","x":590,"y":1963,"width":434,"height":90},"20":{"id":"2078-20-3","x":590,"y":2053,"width":434,"height":88},"21":{"id":"2078-21-3","x":590,"y":2143,"width":434,"height":86}},"4":{"1":{"id":"2078-1-4","x":1018,"y":380,"width":933,"height":97},"2":{"id":"2078-2-4","x":1018,"y":477,"width":933,"height":87},"3":{"id":"2078-3-4","x":1018,"y":562,"width":933,"height":90},"4":{"id":"2078-4-4","x":1018,"y":650,"width":933,"height":88},"5":{"id":"2078-5-4","x":1018,"y":736,"width":934,"height":88},"6":{"id":"2078-6-4","x":1020,"y":826,"width":932,"height":88},"7":{"id":"2078-7-4","x":1020,"y":912,"width":932,"height":90},"8":{"id":"2078-8-4","x":1020,"y":1002,"width":932,"height":88},"9":{"id":"2078-9-4","x":1020,"y":1089,"width":932,"height":88},"10":{"id":"2078-10-4","x":1020,"y":1175,"width":932,"height":88},"11":{"id":"2078-11-4","x":1020,"y":1261,"width":934,"height":90},"12":{"id":"2078-12-4","x":1022,"y":1350,"width":932,"height":89},"13":{"id":"2078-13-4","x":1022,"y":1438,"width":932,"height":91},"14":{"id":"2078-14-4","x":1022,"y":1528,"width":932,"height":89},"15":{"id":"2078-15-4","x":1022,"y":1616,"width":932,"height":88},"16":{"id":"2078-16-4","x":1022,"y":1702,"width":932,"height":88},"17":{"id":"2078-17-4","x":1022,"y":1788,"width":934,"height":89},"18":{"id":"2078-18-4","x":1024,"y":1875,"width":932,"height":88},"19":{"id":"2078-19-4","x":1024,"y":1963,"width":932,"height":88},"20":{"id":"2078-20-4","x":1024,"y":2053,"width":932,"height":86},"21":{"id":"2078-21-4","x":1024,"y":2141,"width":932,"height":86}},"5":{"1":{"id":"2078-1-5","x":1951,"y":380,"width":340,"height":97},"2":{"id":"2078-2-5","x":1951,"y":477,"width":340,"height":87},"3":{"id":"2078-3-5","x":1951,"y":564,"width":340,"height":88},"4":{"id":"2078-4-5","x":1951,"y":652,"width":340,"height":86},"5":{"id":"2078-5-5","x":1951,"y":738,"width":340,"height":86},"6":{"id":"2078-6-5","x":1952,"y":824,"width":339,"height":90},"7":{"id":"2078-7-5","x":1952,"y":914,"width":339,"height":88},"8":{"id":"2078-8-5","x":1952,"y":1002,"width":339,"height":88},"9":{"id":"2078-9-5","x":1952,"y":1090,"width":339,"height":87},"10":{"id":"2078-10-5","x":1952,"y":1177,"width":339,"height":86},"11":{"id":"2078-11-5","x":1952,"y":1263,"width":341,"height":88},"12":{"id":"2078-12-5","x":1954,"y":1351,"width":339,"height":88},"13":{"id":"2078-13-5","x":1954,"y":1439,"width":339,"height":90},"14":{"id":"2078-14-5","x":1954,"y":1529,"width":339,"height":88},"15":{"id":"2078-15-5","x":1954,"y":1617,"width":339,"height":87},"16":{"id":"2078-16-5","x":1954,"y":1704,"width":339,"height":86},"17":{"id":"2078-17-5","x":1954,"y":1790,"width":339,"height":87},"18":{"id":"2078-18-5","x":1956,"y":1877,"width":337,"height":86},"19":{"id":"2078-19-5","x":1956,"y":1963,"width":337,"height":88},"20":{"id":"2078-20-5","x":1956,"y":2051,"width":337,"height":88},"21":{"id":"2078-21-5","x":1956,"y":2139,"width":337,"height":88}},"6":{"1":{"id":"2078-1-6","x":2291,"y":380,"width":239,"height":97},"2":{"id":"2078-2-6","x":2291,"y":477,"width":239,"height":87},"3":{"id":"2078-3-6","x":2291,"y":564,"width":239,"height":88},"4":{"id":"2078-4-6","x":2291,"y":652,"width":239,"height":86},"5":{"id":"2078-5-6","x":2291,"y":738,"width":241,"height":86},"6":{"id":"2078-6-6","x":2291,"y":824,"width":241,"height":90},"7":{"id":"2078-7-6","x":2291,"y":914,"width":241,"height":88},"8":{"id":"2078-8-6","x":2291,"y":1002,"width":241,"height":88},"9":{"id":"2078-9-6","x":2291,"y":1090,"width":241,"height":87},"10":{"id":"2078-10-6","x":2291,"y":1177,"width":241,"height":86},"11":{"id":"2078-11-6","x":2291,"y":1263,"width":241,"height":88},"12":{"id":"2078-12-6","x":2293,"y":1351,"width":239,"height":88},"13":{"id":"2078-13-6","x":2293,"y":1439,"width":239,"height":90},"14":{"id":"2078-14-6","x":2293,"y":1529,"width":239,"height":88},"15":{"id":"2078-15-6","x":2293,"y":1617,"width":239,"height":87},"16":{"id":"2078-16-6","x":2293,"y":1704,"width":239,"height":86},"17":{"id":"2078-17-6","x":2293,"y":1790,"width":241,"height":87},"18":{"id":"2078-18-6","x":2293,"y":1877,"width":241,"height":86},"19":{"id":"2078-19-6","x":2293,"y":1963,"width":241,"height":88},"20":{"id":"2078-20-6","x":2293,"y":2051,"width":241,"height":88},"21":{"id":"2078-21-6","x":2293,"y":2139,"width":241,"height":88}},"7":{"1":{"id":"2078-1-7","x":2530,"y":380,"width":240,"height":97},"2":{"id":"2078-2-7","x":2530,"y":477,"width":240,"height":87},"3":{"id":"2078-3-7","x":2530,"y":564,"width":240,"height":88},"4":{"id":"2078-4-7","x":2530,"y":652,"width":240,"height":86},"5":{"id":"2078-5-7","x":2530,"y":738,"width":242,"height":86},"6":{"id":"2078-6-7","x":2532,"y":824,"width":240,"height":90},"7":{"id":"2078-7-7","x":2532,"y":914,"width":240,"height":88},"8":{"id":"2078-8-7","x":2532,"y":1002,"width":240,"height":88},"9":{"id":"2078-9-7","x":2532,"y":1090,"width":240,"height":87},"10":{"id":"2078-10-7","x":2532,"y":1177,"width":240,"height":86},"11":{"id":"2078-11-7","x":2532,"y":1263,"width":242,"height":88},"12":{"id":"2078-12-7","x":2532,"y":1351,"width":242,"height":88},"13":{"id":"2078-13-7","x":2532,"y":1439,"width":242,"height":92},"14":{"id":"2078-14-7","x":2532,"y":1529,"width":242,"height":90},"15":{"id":"2078-15-7","x":2532,"y":1617,"width":242,"height":89},"16":{"id":"2078-16-7","x":2532,"y":1704,"width":242,"height":88},"17":{"id":"2078-17-7","x":2532,"y":1790,"width":243,"height":87},"18":{"id":"2078-18-7","x":2534,"y":1877,"width":241,"height":86},"19":{"id":"2078-19-7","x":2534,"y":1963,"width":241,"height":88},"20":{"id":"2078-20-7","x":2534,"y":2051,"width":241,"height":86},"21":{"id":"2078-21-7","x":2534,"y":2139,"width":241,"height":87}},"8":{"1":{"id":"2078-1-8","x":2770,"y":380,"width":196,"height":97},"2":{"id":"2078-2-8","x":2770,"y":477,"width":196,"height":87},"3":{"id":"2078-3-8","x":2770,"y":564,"width":196,"height":88},"4":{"id":"2078-4-8","x":2770,"y":652,"width":196,"height":86},"5":{"id":"2078-5-8","x":2770,"y":738,"width":198,"height":86},"6":{"id":"2078-6-8","x":2772,"y":824,"width":196,"height":90},"7":{"id":"2078-7-8","x":2772,"y":914,"width":196,"height":88},"8":{"id":"2078-8-8","x":2772,"y":1002,"width":196,"height":88},"9":{"id":"2078-9-8","x":2772,"y":1090,"width":196,"height":87},"10":{"id":"2078-10-8","x":2772,"y":1177,"width":196,"height":86},"11":{"id":"2078-11-8","x":2772,"y":1263,"width":197,"height":88},"12":{"id":"2078-12-8","x":2774,"y":1351,"width":195,"height":88},"13":{"id":"2078-13-8","x":2774,"y":1439,"width":195,"height":92},"14":{"id":"2078-14-8","x":2774,"y":1531,"width":195,"height":88},"15":{"id":"2078-15-8","x":2774,"y":1619,"width":195,"height":87},"16":{"id":"2078-16-8","x":2774,"y":1706,"width":195,"height":86},"17":{"id":"2078-17-8","x":2774,"y":1792,"width":197,"height":85},"18":{"id":"2078-18-8","x":2775,"y":1877,"width":196,"height":86},"19":{"id":"2078-19-8","x":2775,"y":1963,"width":196,"height":88},"20":{"id":"2078-20-8","x":2775,"y":2051,"width":196,"height":86},"21":{"id":"2078-21-8","x":2775,"y":2137,"width":196,"height":89}},"9":{"1":{"id":"2078-1-9","x":2966,"y":380,"width":370,"height":97},"2":{"id":"2078-2-9","x":2966,"y":477,"width":370,"height":87},"3":{"id":"2078-3-9","x":2966,"y":564,"width":370,"height":88},"4":{"id":"2078-4-9","x":2966,"y":652,"width":370,"height":86},"5":{"id":"2078-5-9","x":2966,"y":738,"width":372,"height":86},"6":{"id":"2078-6-9","x":2968,"y":824,"width":370,"height":90},"7":{"id":"2078-7-9","x":2968,"y":914,"width":370,"height":88},"8":{"id":"2078-8-9","x":2968,"y":1002,"width":370,"height":88},"9":{"id":"2078-9-9","x":2968,"y":1090,"width":370,"height":87},"10":{"id":"2078-10-9","x":2968,"y":1177,"width":370,"height":86},"11":{"id":"2078-11-9","x":2968,"y":1263,"width":371,"height":88},"12":{"id":"2078-12-9","x":2969,"y":1351,"width":370,"height":90},"13":{"id":"2078-13-9","x":2969,"y":1439,"width":370,"height":92},"14":{"id":"2078-14-9","x":2969,"y":1531,"width":370,"height":88},"15":{"id":"2078-15-9","x":2969,"y":1619,"width":370,"height":87},"16":{"id":"2078-16-9","x":2969,"y":1706,"width":370,"height":86},"17":{"id":"2078-17-9","x":2969,"y":1792,"width":372,"height":85},"18":{"id":"2078-18-9","x":2971,"y":1877,"width":370,"height":86},"19":{"id":"2078-19-9","x":2971,"y":1963,"width":370,"height":86},"20":{"id":"2078-20-9","x":2971,"y":2051,"width":370,"height":86},"21":{"id":"2078-21-9","x":2971,"y":2137,"width":370,"height":89}}},"cellCount":189}