{"image_id":"2452","document":"\u738b\u60e0\u7f8e\/\u500b\u4eba\u6350\u8d08\u6536\u5165\/\u738b\u60e0\u7f8e\u500b\u4eba\u6350\u8d08\u6536\u5165.pdf","page_no":"001","url":"http:\/\/pic.pimg.tw\/ronnywang\/1393701177-2134186100.jpg?v=1393701183","width":"7020","height":"4964","cells":{"1":{"1":{"id":"2452-1-1","x":281,"y":724,"width":335,"height":190},"2":{"id":"2452-1-2","x":281,"y":914,"width":335,"height":173},"3":{"id":"2452-1-3","x":281,"y":1087,"width":335,"height":178},"4":{"id":"2452-1-4","x":281,"y":1265,"width":335,"height":181},"5":{"id":"2452-1-5","x":281,"y":1446,"width":335,"height":180},"6":{"id":"2452-1-6","x":281,"y":1626,"width":335,"height":177},"7":{"id":"2452-1-7","x":281,"y":1803,"width":335,"height":177},"8":{"id":"2452-1-8","x":281,"y":1980,"width":335,"height":174},"9":{"id":"2452-1-9","x":281,"y":2154,"width":335,"height":175},"10":{"id":"2452-1-10","x":281,"y":2329,"width":335,"height":179},"11":{"id":"2452-1-11","x":281,"y":2508,"width":335,"height":178},"12":{"id":"2452-1-12","x":281,"y":2686,"width":335,"height":176},"13":{"id":"2452-1-13","x":281,"y":2862,"width":335,"height":177},"14":{"id":"2452-1-14","x":281,"y":3039,"width":335,"height":175},"15":{"id":"2452-1-15","x":281,"y":3214,"width":335,"height":175},"16":{"id":"2452-1-16","x":281,"y":3389,"width":335,"height":178},"17":{"id":"2452-1-17","x":281,"y":3567,"width":335,"height":179},"18":{"id":"2452-1-18","x":281,"y":3746,"width":335,"height":179},"19":{"id":"2452-1-19","x":281,"y":3925,"width":335,"height":177},"20":{"id":"2452-1-20","x":281,"y":4102,"width":335,"height":174},"21":{"id":"2452-1-21","x":281,"y":4276,"width":335,"height":170},"22":{"id":"2452-1-22","x":281,"y":4446,"width":335,"height":114}},"2":{"1":{"id":"2452-2-1","x":616,"y":724,"width":576,"height":190},"2":{"id":"2452-2-2","x":616,"y":914,"width":576,"height":173},"3":{"id":"2452-2-3","x":616,"y":1087,"width":576,"height":178},"4":{"id":"2452-2-4","x":616,"y":1265,"width":576,"height":181},"5":{"id":"2452-2-5","x":616,"y":1446,"width":576,"height":180},"6":{"id":"2452-2-6","x":616,"y":1626,"width":576,"height":177},"7":{"id":"2452-2-7","x":616,"y":1803,"width":576,"height":177},"8":{"id":"2452-2-8","x":616,"y":1980,"width":576,"height":174},"9":{"id":"2452-2-9","x":616,"y":2154,"width":576,"height":175},"10":{"id":"2452-2-10","x":616,"y":2329,"width":576,"height":179},"11":{"id":"2452-2-11","x":616,"y":2508,"width":576,"height":178},"12":{"id":"2452-2-12","x":616,"y":2686,"width":576,"height":176},"13":{"id":"2452-2-13","x":616,"y":2862,"width":576,"height":177},"14":{"id":"2452-2-14","x":616,"y":3039,"width":576,"height":175},"15":{"id":"2452-2-15","x":616,"y":3214,"width":576,"height":175},"16":{"id":"2452-2-16","x":616,"y":3389,"width":576,"height":178},"17":{"id":"2452-2-17","x":616,"y":3567,"width":576,"height":179},"18":{"id":"2452-2-18","x":616,"y":3746,"width":576,"height":179},"19":{"id":"2452-2-19","x":616,"y":3925,"width":576,"height":177},"20":{"id":"2452-2-20","x":616,"y":4102,"width":576,"height":174},"21":{"id":"2452-2-21","x":616,"y":4276,"width":576,"height":170},"22":{"id":"2452-2-22","x":616,"y":4446,"width":576,"height":105}},"3":{"1":{"id":"2452-3-1","x":1192,"y":724,"width":866,"height":190},"2":{"id":"2452-3-2","x":1192,"y":914,"width":866,"height":173},"3":{"id":"2452-3-3","x":1192,"y":1087,"width":866,"height":178},"4":{"id":"2452-3-4","x":1192,"y":1265,"width":866,"height":181},"5":{"id":"2452-3-5","x":1192,"y":1446,"width":866,"height":180},"6":{"id":"2452-3-6","x":1192,"y":1626,"width":866,"height":177},"7":{"id":"2452-3-7","x":1192,"y":1803,"width":866,"height":177},"8":{"id":"2452-3-8","x":1192,"y":1980,"width":866,"height":174},"9":{"id":"2452-3-9","x":1192,"y":2154,"width":866,"height":175},"10":{"id":"2452-3-10","x":1192,"y":2329,"width":866,"height":179},"11":{"id":"2452-3-11","x":1192,"y":2508,"width":866,"height":178},"12":{"id":"2452-3-12","x":1192,"y":2686,"width":866,"height":176},"13":{"id":"2452-3-13","x":1192,"y":2862,"width":866,"height":177},"14":{"id":"2452-3-14","x":1192,"y":3039,"width":866,"height":175},"15":{"id":"2452-3-15","x":1192,"y":3214,"width":866,"height":175},"16":{"id":"2452-3-16","x":1192,"y":3389,"width":866,"height":178},"17":{"id":"2452-3-17","x":1192,"y":3567,"width":866,"height":179},"18":{"id":"2452-3-18","x":1192,"y":3746,"width":866,"height":179},"19":{"id":"2452-3-19","x":1192,"y":3925,"width":866,"height":177},"20":{"id":"2452-3-20","x":1192,"y":4102,"width":866,"height":174},"21":{"id":"2452-3-21","x":1192,"y":4276,"width":866,"height":170},"22":{"id":"2452-3-22","x":1192,"y":4446,"width":866,"height":91}},"4":{"1":{"id":"2452-4-1","x":2058,"y":724,"width":1868,"height":190},"2":{"id":"2452-4-2","x":2058,"y":914,"width":1868,"height":173},"3":{"id":"2452-4-3","x":2058,"y":1087,"width":1868,"height":178},"4":{"id":"2452-4-4","x":2058,"y":1265,"width":1868,"height":181},"5":{"id":"2452-4-5","x":2058,"y":1446,"width":1868,"height":180},"6":{"id":"2452-4-6","x":2058,"y":1626,"width":1868,"height":177},"7":{"id":"2452-4-7","x":2058,"y":1803,"width":1868,"height":177},"8":{"id":"2452-4-8","x":2058,"y":1980,"width":1868,"height":174},"9":{"id":"2452-4-9","x":2058,"y":2154,"width":1868,"height":175},"10":{"id":"2452-4-10","x":2058,"y":2329,"width":1868,"height":179},"11":{"id":"2452-4-11","x":2058,"y":2508,"width":1868,"height":178},"12":{"id":"2452-4-12","x":2058,"y":2686,"width":1868,"height":176},"13":{"id":"2452-4-13","x":2058,"y":2862,"width":1868,"height":177},"14":{"id":"2452-4-14","x":2058,"y":3039,"width":1868,"height":175},"15":{"id":"2452-4-15","x":2058,"y":3214,"width":1868,"height":175},"16":{"id":"2452-4-16","x":2058,"y":3389,"width":1868,"height":178},"17":{"id":"2452-4-17","x":2058,"y":3567,"width":1868,"height":179},"18":{"id":"2452-4-18","x":2058,"y":3746,"width":1868,"height":179},"19":{"id":"2452-4-19","x":2058,"y":3925,"width":1868,"height":177},"20":{"id":"2452-4-20","x":2058,"y":4102,"width":1868,"height":174},"21":{"id":"2452-4-21","x":2058,"y":4276,"width":1868,"height":170},"22":{"id":"2452-4-22","x":2058,"y":4446,"width":1868,"height":61}},"5":{"1":{"id":"2452-5-1","x":3926,"y":724,"width":682,"height":190},"2":{"id":"2452-5-2","x":3926,"y":914,"width":682,"height":173},"3":{"id":"2452-5-3","x":3926,"y":1087,"width":682,"height":178},"4":{"id":"2452-5-4","x":3926,"y":1265,"width":682,"height":181},"5":{"id":"2452-5-5","x":3926,"y":1446,"width":682,"height":180},"6":{"id":"2452-5-6","x":3926,"y":1626,"width":682,"height":177},"7":{"id":"2452-5-7","x":3926,"y":1803,"width":682,"height":177},"8":{"id":"2452-5-8","x":3926,"y":1980,"width":682,"height":174},"9":{"id":"2452-5-9","x":3926,"y":2154,"width":682,"height":175},"10":{"id":"2452-5-10","x":3926,"y":2329,"width":682,"height":179},"11":{"id":"2452-5-11","x":3926,"y":2508,"width":682,"height":178},"12":{"id":"2452-5-12","x":3926,"y":2686,"width":682,"height":176},"13":{"id":"2452-5-13","x":3926,"y":2862,"width":682,"height":177},"14":{"id":"2452-5-14","x":3926,"y":3039,"width":682,"height":175},"15":{"id":"2452-5-15","x":3926,"y":3214,"width":682,"height":175},"16":{"id":"2452-5-16","x":3926,"y":3389,"width":682,"height":178},"17":{"id":"2452-5-17","x":3926,"y":3567,"width":682,"height":179},"18":{"id":"2452-5-18","x":3926,"y":3746,"width":682,"height":179},"19":{"id":"2452-5-19","x":3926,"y":3925,"width":682,"height":177},"20":{"id":"2452-5-20","x":3926,"y":4102,"width":682,"height":174},"21":{"id":"2452-5-21","x":3926,"y":4276,"width":682,"height":170},"22":{"id":"2452-5-22","x":3926,"y":4446,"width":682,"height":50}},"6":{"1":{"id":"2452-6-1","x":4608,"y":724,"width":482,"height":190},"2":{"id":"2452-6-2","x":4608,"y":914,"width":482,"height":173},"3":{"id":"2452-6-3","x":4608,"y":1087,"width":482,"height":178},"4":{"id":"2452-6-4","x":4608,"y":1265,"width":482,"height":181},"5":{"id":"2452-6-5","x":4608,"y":1446,"width":482,"height":180},"6":{"id":"2452-6-6","x":4608,"y":1626,"width":482,"height":177},"7":{"id":"2452-6-7","x":4608,"y":1803,"width":482,"height":177},"8":{"id":"2452-6-8","x":4608,"y":1980,"width":481,"height":174},"9":{"id":"2452-6-9","x":4608,"y":2154,"width":481,"height":175},"10":{"id":"2452-6-10","x":4608,"y":2329,"width":481,"height":179},"11":{"id":"2452-6-11","x":4608,"y":2508,"width":481,"height":178},"12":{"id":"2452-6-12","x":4608,"y":2686,"width":481,"height":176},"13":{"id":"2452-6-13","x":4608,"y":2862,"width":481,"height":177},"14":{"id":"2452-6-14","x":4608,"y":3039,"width":481,"height":175},"15":{"id":"2452-6-15","x":4608,"y":3214,"width":481,"height":175},"16":{"id":"2452-6-16","x":4608,"y":3389,"width":481,"height":178},"17":{"id":"2452-6-17","x":4608,"y":3567,"width":481,"height":179},"18":{"id":"2452-6-18","x":4608,"y":3746,"width":481,"height":179},"19":{"id":"2452-6-19","x":4608,"y":3925,"width":481,"height":177},"20":{"id":"2452-6-20","x":4608,"y":4102,"width":481,"height":174},"21":{"id":"2452-6-21","x":4608,"y":4276,"width":481,"height":170},"22":{"id":"2452-6-22","x":4608,"y":4446,"width":481,"height":43}},"7":{"1":{"id":"2452-7-1","x":5090,"y":724,"width":482,"height":190},"2":{"id":"2452-7-2","x":5090,"y":914,"width":482,"height":173},"3":{"id":"2452-7-3","x":5090,"y":1087,"width":482,"height":178},"4":{"id":"2452-7-4","x":5090,"y":1265,"width":482,"height":181},"5":{"id":"2452-7-5","x":5090,"y":1446,"width":482,"height":180},"6":{"id":"2452-7-6","x":5090,"y":1626,"width":482,"height":177},"7":{"id":"2452-7-7","x":5090,"y":1803,"width":482,"height":177},"8":{"id":"2452-7-8","x":5090,"y":1980,"width":481,"height":174},"9":{"id":"2452-7-9","x":5089,"y":2154,"width":482,"height":175},"10":{"id":"2452-7-10","x":5089,"y":2329,"width":482,"height":179},"11":{"id":"2452-7-11","x":5089,"y":2508,"width":482,"height":178},"12":{"id":"2452-7-12","x":5089,"y":2686,"width":482,"height":176},"13":{"id":"2452-7-13","x":5089,"y":2862,"width":482,"height":177},"14":{"id":"2452-7-14","x":5089,"y":3039,"width":482,"height":175},"15":{"id":"2452-7-15","x":5089,"y":3214,"width":482,"height":175},"16":{"id":"2452-7-16","x":5089,"y":3389,"width":482,"height":178},"17":{"id":"2452-7-17","x":5089,"y":3567,"width":482,"height":179},"18":{"id":"2452-7-18","x":5089,"y":3746,"width":482,"height":179},"19":{"id":"2452-7-19","x":5089,"y":3925,"width":482,"height":177},"20":{"id":"2452-7-20","x":5089,"y":4102,"width":482,"height":174},"21":{"id":"2452-7-21","x":5089,"y":4276,"width":482,"height":170},"22":{"id":"2452-7-22","x":5089,"y":4446,"width":482,"height":35}},"8":{"1":{"id":"2452-8-1","x":5572,"y":724,"width":393,"height":190},"2":{"id":"2452-8-2","x":5572,"y":914,"width":393,"height":173},"3":{"id":"2452-8-3","x":5572,"y":1087,"width":393,"height":178},"4":{"id":"2452-8-4","x":5572,"y":1265,"width":393,"height":181},"5":{"id":"2452-8-5","x":5572,"y":1446,"width":393,"height":180},"6":{"id":"2452-8-6","x":5572,"y":1626,"width":393,"height":177},"7":{"id":"2452-8-7","x":5572,"y":1803,"width":393,"height":177},"8":{"id":"2452-8-8","x":5572,"y":1980,"width":393,"height":174},"9":{"id":"2452-8-9","x":5571,"y":2154,"width":394,"height":175},"10":{"id":"2452-8-10","x":5571,"y":2329,"width":394,"height":179},"11":{"id":"2452-8-11","x":5571,"y":2508,"width":394,"height":178},"12":{"id":"2452-8-12","x":5571,"y":2686,"width":394,"height":176},"13":{"id":"2452-8-13","x":5571,"y":2862,"width":394,"height":177},"14":{"id":"2452-8-14","x":5571,"y":3039,"width":394,"height":175},"15":{"id":"2452-8-15","x":5571,"y":3214,"width":394,"height":175},"16":{"id":"2452-8-16","x":5571,"y":3389,"width":394,"height":178},"17":{"id":"2452-8-17","x":5571,"y":3567,"width":394,"height":179},"18":{"id":"2452-8-18","x":5571,"y":3746,"width":394,"height":179},"19":{"id":"2452-8-19","x":5571,"y":3925,"width":394,"height":177},"20":{"id":"2452-8-20","x":5571,"y":4102,"width":394,"height":174},"21":{"id":"2452-8-21","x":5571,"y":4276,"width":394,"height":170},"22":{"id":"2452-8-22","x":5571,"y":4446,"width":394,"height":29}},"9":{"1":{"id":"2452-9-1","x":5965,"y":724,"width":754,"height":190},"2":{"id":"2452-9-2","x":5965,"y":914,"width":754,"height":173},"3":{"id":"2452-9-3","x":5965,"y":1087,"width":754,"height":178},"4":{"id":"2452-9-4","x":5965,"y":1265,"width":754,"height":181},"5":{"id":"2452-9-5","x":5965,"y":1446,"width":754,"height":180},"6":{"id":"2452-9-6","x":5965,"y":1626,"width":754,"height":177},"7":{"id":"2452-9-7","x":5965,"y":1803,"width":754,"height":177},"8":{"id":"2452-9-8","x":5965,"y":1980,"width":754,"height":174},"9":{"id":"2452-9-9","x":5965,"y":2154,"width":754,"height":175},"10":{"id":"2452-9-10","x":5965,"y":2329,"width":754,"height":179},"11":{"id":"2452-9-11","x":5965,"y":2508,"width":754,"height":178},"12":{"id":"2452-9-12","x":5965,"y":2686,"width":754,"height":176},"13":{"id":"2452-9-13","x":5965,"y":2862,"width":754,"height":177},"14":{"id":"2452-9-14","x":5965,"y":3039,"width":754,"height":175},"15":{"id":"2452-9-15","x":5965,"y":3214,"width":754,"height":175},"16":{"id":"2452-9-16","x":5965,"y":3389,"width":754,"height":178},"17":{"id":"2452-9-17","x":5965,"y":3567,"width":754,"height":179},"18":{"id":"2452-9-18","x":5965,"y":3746,"width":754,"height":179},"19":{"id":"2452-9-19","x":5965,"y":3925,"width":754,"height":177},"20":{"id":"2452-9-20","x":5965,"y":4102,"width":754,"height":174},"21":{"id":"2452-9-21","x":5965,"y":4276,"width":754,"height":170},"22":{"id":"2452-9-22","x":5965,"y":4446,"width":754,"height":17}}}}