{"image_id":"2520","document":"\u4e01\u5b88\u4e2d\/\u96dc\u652f\u652f\u51fa\/\u96dc\u652f\u652f\u51fa.pdf","page_no":"004","url":"http:\/\/pic.pimg.tw\/ronnywang\/1393705113-3314350133.jpg?v=1393705118","width":"7020","height":"4964","cells":{"1":{"1":{"id":"2520-1-1","x":251,"y":587,"width":340,"height":195},"2":{"id":"2520-1-2","x":251,"y":782,"width":340,"height":176},"3":{"id":"2520-1-3","x":251,"y":958,"width":340,"height":178},"4":{"id":"2520-1-4","x":251,"y":1136,"width":340,"height":176},"5":{"id":"2520-1-5","x":251,"y":1312,"width":340,"height":176},"6":{"id":"2520-1-6","x":251,"y":1488,"width":340,"height":178},"7":{"id":"2520-1-7","x":251,"y":1666,"width":340,"height":181},"8":{"id":"2520-1-8","x":251,"y":1847,"width":340,"height":179},"9":{"id":"2520-1-9","x":251,"y":2026,"width":340,"height":179},"10":{"id":"2520-1-10","x":251,"y":2205,"width":340,"height":178},"11":{"id":"2520-1-11","x":251,"y":2383,"width":340,"height":172},"12":{"id":"2520-1-12","x":251,"y":2555,"width":340,"height":179},"13":{"id":"2520-1-13","x":251,"y":2734,"width":340,"height":177},"14":{"id":"2520-1-14","x":251,"y":2911,"width":340,"height":180},"15":{"id":"2520-1-15","x":251,"y":3091,"width":340,"height":178},"16":{"id":"2520-1-16","x":251,"y":3269,"width":340,"height":178},"17":{"id":"2520-1-17","x":251,"y":3447,"width":340,"height":175},"18":{"id":"2520-1-18","x":251,"y":3622,"width":340,"height":178},"19":{"id":"2520-1-19","x":251,"y":3800,"width":340,"height":178},"20":{"id":"2520-1-20","x":251,"y":3978,"width":340,"height":180},"21":{"id":"2520-1-21","x":251,"y":4158,"width":340,"height":175},"22":{"id":"2520-1-22","x":251,"y":4333,"width":340,"height":112},"23":{"id":"2520-1-23","x":251,"y":4450,"width":340,"height":458}},"2":{"1":{"id":"2520-2-1","x":591,"y":587,"width":587,"height":195},"2":{"id":"2520-2-2","x":591,"y":782,"width":587,"height":176},"3":{"id":"2520-2-3","x":591,"y":958,"width":587,"height":178},"4":{"id":"2520-2-4","x":591,"y":1136,"width":587,"height":176},"5":{"id":"2520-2-5","x":591,"y":1312,"width":587,"height":176},"6":{"id":"2520-2-6","x":591,"y":1488,"width":587,"height":178},"7":{"id":"2520-2-7","x":591,"y":1666,"width":587,"height":181},"8":{"id":"2520-2-8","x":591,"y":1847,"width":587,"height":179},"9":{"id":"2520-2-9","x":591,"y":2026,"width":587,"height":179},"10":{"id":"2520-2-10","x":591,"y":2205,"width":587,"height":178},"11":{"id":"2520-2-11","x":591,"y":2383,"width":587,"height":172},"12":{"id":"2520-2-12","x":591,"y":2555,"width":587,"height":179},"13":{"id":"2520-2-13","x":591,"y":2734,"width":587,"height":177},"14":{"id":"2520-2-14","x":591,"y":2911,"width":587,"height":180},"15":{"id":"2520-2-15","x":591,"y":3091,"width":587,"height":178},"16":{"id":"2520-2-16","x":591,"y":3269,"width":587,"height":178},"17":{"id":"2520-2-17","x":591,"y":3447,"width":587,"height":175},"18":{"id":"2520-2-18","x":591,"y":3622,"width":587,"height":178},"19":{"id":"2520-2-19","x":591,"y":3800,"width":587,"height":178},"20":{"id":"2520-2-20","x":591,"y":3978,"width":587,"height":180},"21":{"id":"2520-2-21","x":591,"y":4158,"width":587,"height":175},"22":{"id":"2520-2-22","x":591,"y":4333,"width":587,"height":102},"23":{"id":"2520-2-23","x":591,"y":4445,"width":587,"height":463}},"3":{"1":{"id":"2520-3-1","x":1178,"y":587,"width":873,"height":195},"2":{"id":"2520-3-2","x":1178,"y":782,"width":873,"height":176},"3":{"id":"2520-3-3","x":1178,"y":958,"width":873,"height":178},"4":{"id":"2520-3-4","x":1178,"y":1136,"width":873,"height":176},"5":{"id":"2520-3-5","x":1178,"y":1312,"width":873,"height":176},"6":{"id":"2520-3-6","x":1178,"y":1488,"width":873,"height":178},"7":{"id":"2520-3-7","x":1178,"y":1666,"width":873,"height":181},"8":{"id":"2520-3-8","x":1178,"y":1847,"width":873,"height":179},"9":{"id":"2520-3-9","x":1178,"y":2026,"width":873,"height":179},"10":{"id":"2520-3-10","x":1178,"y":2205,"width":873,"height":178},"11":{"id":"2520-3-11","x":1178,"y":2383,"width":873,"height":172},"12":{"id":"2520-3-12","x":1178,"y":2555,"width":873,"height":179},"13":{"id":"2520-3-13","x":1178,"y":2734,"width":873,"height":177},"14":{"id":"2520-3-14","x":1178,"y":2911,"width":873,"height":180},"15":{"id":"2520-3-15","x":1178,"y":3091,"width":873,"height":178},"16":{"id":"2520-3-16","x":1178,"y":3269,"width":873,"height":178},"17":{"id":"2520-3-17","x":1178,"y":3447,"width":873,"height":175},"18":{"id":"2520-3-18","x":1178,"y":3622,"width":873,"height":178},"19":{"id":"2520-3-19","x":1178,"y":3800,"width":873,"height":178},"20":{"id":"2520-3-20","x":1178,"y":3978,"width":873,"height":180},"21":{"id":"2520-3-21","x":1178,"y":4158,"width":873,"height":175},"22":{"id":"2520-3-22","x":1178,"y":4333,"width":873,"height":88},"23":{"id":"2520-3-23","x":1178,"y":4435,"width":873,"height":473}},"4":{"1":{"id":"2520-4-1","x":2051,"y":587,"width":1876,"height":195},"2":{"id":"2520-4-2","x":2051,"y":782,"width":1876,"height":176},"3":{"id":"2520-4-3","x":2051,"y":958,"width":1876,"height":178},"4":{"id":"2520-4-4","x":2051,"y":1136,"width":1876,"height":176},"5":{"id":"2520-4-5","x":2051,"y":1312,"width":1876,"height":176},"6":{"id":"2520-4-6","x":2051,"y":1488,"width":1876,"height":178},"7":{"id":"2520-4-7","x":2051,"y":1666,"width":1876,"height":181},"8":{"id":"2520-4-8","x":2051,"y":1847,"width":1876,"height":179},"9":{"id":"2520-4-9","x":2051,"y":2026,"width":1876,"height":179},"10":{"id":"2520-4-10","x":2051,"y":2205,"width":1876,"height":178},"11":{"id":"2520-4-11","x":2051,"y":2383,"width":1876,"height":172},"12":{"id":"2520-4-12","x":2051,"y":2555,"width":1876,"height":179},"13":{"id":"2520-4-13","x":2051,"y":2734,"width":1876,"height":177},"14":{"id":"2520-4-14","x":2051,"y":2911,"width":1876,"height":180},"15":{"id":"2520-4-15","x":2051,"y":3091,"width":1876,"height":178},"16":{"id":"2520-4-16","x":2051,"y":3269,"width":1876,"height":178},"17":{"id":"2520-4-17","x":2051,"y":3447,"width":1876,"height":175},"18":{"id":"2520-4-18","x":2051,"y":3622,"width":1876,"height":178},"19":{"id":"2520-4-19","x":2051,"y":3800,"width":1876,"height":178},"20":{"id":"2520-4-20","x":2051,"y":3978,"width":1876,"height":180},"21":{"id":"2520-4-21","x":2051,"y":4158,"width":1876,"height":175},"22":{"id":"2520-4-22","x":2051,"y":4333,"width":1876,"height":57},"23":{"id":"2520-4-23","x":2051,"y":4421,"width":1876,"height":487}},"5":{"1":{"id":"2520-5-1","x":3927,"y":587,"width":681,"height":195},"2":{"id":"2520-5-2","x":3927,"y":782,"width":681,"height":176},"3":{"id":"2520-5-3","x":3927,"y":958,"width":681,"height":178},"4":{"id":"2520-5-4","x":3927,"y":1136,"width":681,"height":176},"5":{"id":"2520-5-5","x":3927,"y":1312,"width":681,"height":176},"6":{"id":"2520-5-6","x":3927,"y":1488,"width":681,"height":178},"7":{"id":"2520-5-7","x":3927,"y":1666,"width":681,"height":181},"8":{"id":"2520-5-8","x":3927,"y":1847,"width":681,"height":179},"9":{"id":"2520-5-9","x":3927,"y":2026,"width":681,"height":179},"10":{"id":"2520-5-10","x":3927,"y":2205,"width":681,"height":178},"11":{"id":"2520-5-11","x":3927,"y":2383,"width":681,"height":172},"12":{"id":"2520-5-12","x":3927,"y":2555,"width":681,"height":179},"13":{"id":"2520-5-13","x":3927,"y":2734,"width":681,"height":177},"14":{"id":"2520-5-14","x":3927,"y":2911,"width":681,"height":180},"15":{"id":"2520-5-15","x":3927,"y":3091,"width":681,"height":178},"16":{"id":"2520-5-16","x":3927,"y":3269,"width":681,"height":178},"17":{"id":"2520-5-17","x":3927,"y":3447,"width":681,"height":175},"18":{"id":"2520-5-18","x":3927,"y":3622,"width":681,"height":178},"19":{"id":"2520-5-19","x":3927,"y":3800,"width":681,"height":178},"20":{"id":"2520-5-20","x":3927,"y":3978,"width":681,"height":180},"21":{"id":"2520-5-21","x":3927,"y":4158,"width":681,"height":175},"22":{"id":"2520-5-22","x":3927,"y":4333,"width":681,"height":46},"23":{"id":"2520-5-23","x":3927,"y":4390,"width":681,"height":518}},"6":{"1":{"id":"2520-6-1","x":4608,"y":587,"width":483,"height":195},"2":{"id":"2520-6-2","x":4608,"y":782,"width":483,"height":176},"3":{"id":"2520-6-3","x":4608,"y":958,"width":483,"height":178},"4":{"id":"2520-6-4","x":4608,"y":1136,"width":483,"height":176},"5":{"id":"2520-6-5","x":4608,"y":1312,"width":483,"height":176},"6":{"id":"2520-6-6","x":4608,"y":1488,"width":483,"height":178},"7":{"id":"2520-6-7","x":4608,"y":1666,"width":483,"height":181},"8":{"id":"2520-6-8","x":4608,"y":1847,"width":483,"height":179},"9":{"id":"2520-6-9","x":4608,"y":2026,"width":483,"height":179},"10":{"id":"2520-6-10","x":4608,"y":2205,"width":483,"height":178},"11":{"id":"2520-6-11","x":4608,"y":2383,"width":483,"height":172},"12":{"id":"2520-6-12","x":4608,"y":2555,"width":483,"height":179},"13":{"id":"2520-6-13","x":4608,"y":2734,"width":483,"height":177},"14":{"id":"2520-6-14","x":4608,"y":2911,"width":483,"height":180},"15":{"id":"2520-6-15","x":4608,"y":3091,"width":483,"height":178},"16":{"id":"2520-6-16","x":4608,"y":3269,"width":483,"height":178},"17":{"id":"2520-6-17","x":4608,"y":3447,"width":483,"height":175},"18":{"id":"2520-6-18","x":4608,"y":3622,"width":483,"height":178},"19":{"id":"2520-6-19","x":4608,"y":3800,"width":483,"height":178},"20":{"id":"2520-6-20","x":4608,"y":3978,"width":483,"height":180},"21":{"id":"2520-6-21","x":4608,"y":4158,"width":483,"height":175},"22":{"id":"2520-6-22","x":4608,"y":4333,"width":483,"height":38},"23":{"id":"2520-6-23","x":4608,"y":4379,"width":483,"height":529}},"7":{"1":{"id":"2520-7-1","x":5091,"y":587,"width":482,"height":195},"2":{"id":"2520-7-2","x":5091,"y":782,"width":482,"height":176},"3":{"id":"2520-7-3","x":5091,"y":958,"width":482,"height":178},"4":{"id":"2520-7-4","x":5091,"y":1136,"width":482,"height":176},"5":{"id":"2520-7-5","x":5091,"y":1312,"width":482,"height":176},"6":{"id":"2520-7-6","x":5091,"y":1488,"width":482,"height":178},"7":{"id":"2520-7-7","x":5091,"y":1666,"width":482,"height":181},"8":{"id":"2520-7-8","x":5091,"y":1847,"width":482,"height":179},"9":{"id":"2520-7-9","x":5091,"y":2026,"width":482,"height":179},"10":{"id":"2520-7-10","x":5091,"y":2205,"width":482,"height":178},"11":{"id":"2520-7-11","x":5091,"y":2383,"width":482,"height":172},"12":{"id":"2520-7-12","x":5091,"y":2555,"width":482,"height":179},"13":{"id":"2520-7-13","x":5091,"y":2734,"width":482,"height":177},"14":{"id":"2520-7-14","x":5091,"y":2911,"width":482,"height":180},"15":{"id":"2520-7-15","x":5091,"y":3091,"width":482,"height":178},"16":{"id":"2520-7-16","x":5091,"y":3269,"width":482,"height":178},"17":{"id":"2520-7-17","x":5091,"y":3447,"width":482,"height":175},"18":{"id":"2520-7-18","x":5091,"y":3622,"width":482,"height":178},"19":{"id":"2520-7-19","x":5091,"y":3800,"width":482,"height":178},"20":{"id":"2520-7-20","x":5091,"y":3978,"width":482,"height":180},"21":{"id":"2520-7-21","x":5091,"y":4158,"width":482,"height":175},"22":{"id":"2520-7-22","x":5091,"y":4333,"width":482,"height":30},"23":{"id":"2520-7-23","x":5091,"y":4371,"width":482,"height":537}},"8":{"1":{"id":"2520-8-1","x":5573,"y":587,"width":392,"height":195},"2":{"id":"2520-8-2","x":5573,"y":782,"width":392,"height":176},"3":{"id":"2520-8-3","x":5573,"y":958,"width":392,"height":178},"4":{"id":"2520-8-4","x":5573,"y":1136,"width":392,"height":176},"5":{"id":"2520-8-5","x":5573,"y":1312,"width":392,"height":176},"6":{"id":"2520-8-6","x":5573,"y":1488,"width":392,"height":178},"7":{"id":"2520-8-7","x":5573,"y":1666,"width":392,"height":181},"8":{"id":"2520-8-8","x":5573,"y":1847,"width":392,"height":179},"9":{"id":"2520-8-9","x":5573,"y":2026,"width":392,"height":179},"10":{"id":"2520-8-10","x":5573,"y":2205,"width":392,"height":178},"11":{"id":"2520-8-11","x":5573,"y":2383,"width":392,"height":172},"12":{"id":"2520-8-12","x":5573,"y":2555,"width":392,"height":179},"13":{"id":"2520-8-13","x":5573,"y":2734,"width":392,"height":177},"14":{"id":"2520-8-14","x":5573,"y":2911,"width":392,"height":180},"15":{"id":"2520-8-15","x":5573,"y":3091,"width":392,"height":178},"16":{"id":"2520-8-16","x":5573,"y":3269,"width":392,"height":178},"17":{"id":"2520-8-17","x":5573,"y":3447,"width":392,"height":175},"18":{"id":"2520-8-18","x":5573,"y":3622,"width":392,"height":178},"19":{"id":"2520-8-19","x":5573,"y":3800,"width":392,"height":178},"20":{"id":"2520-8-20","x":5573,"y":3978,"width":392,"height":180},"21":{"id":"2520-8-21","x":5573,"y":4158,"width":392,"height":175},"22":{"id":"2520-8-22","x":5573,"y":4333,"width":392,"height":24},"23":{"id":"2520-8-23","x":5573,"y":4363,"width":392,"height":545}},"9":{"1":{"id":"2520-9-1","x":5965,"y":587,"width":744,"height":195},"2":{"id":"2520-9-2","x":5965,"y":782,"width":744,"height":176},"3":{"id":"2520-9-3","x":5965,"y":958,"width":744,"height":178},"4":{"id":"2520-9-4","x":5965,"y":1136,"width":744,"height":176},"5":{"id":"2520-9-5","x":5965,"y":1312,"width":744,"height":176},"6":{"id":"2520-9-6","x":5965,"y":1488,"width":744,"height":178},"7":{"id":"2520-9-7","x":5965,"y":1666,"width":744,"height":181},"8":{"id":"2520-9-8","x":5965,"y":1847,"width":744,"height":179},"9":{"id":"2520-9-9","x":5965,"y":2026,"width":744,"height":179},"10":{"id":"2520-9-10","x":5965,"y":2205,"width":744,"height":178},"11":{"id":"2520-9-11","x":5965,"y":2383,"width":744,"height":172},"12":{"id":"2520-9-12","x":5965,"y":2555,"width":744,"height":179},"13":{"id":"2520-9-13","x":5965,"y":2734,"width":744,"height":177},"14":{"id":"2520-9-14","x":5965,"y":2911,"width":744,"height":180},"15":{"id":"2520-9-15","x":5965,"y":3091,"width":744,"height":178},"16":{"id":"2520-9-16","x":5965,"y":3269,"width":744,"height":178},"17":{"id":"2520-9-17","x":5965,"y":3447,"width":744,"height":175},"18":{"id":"2520-9-18","x":5965,"y":3622,"width":744,"height":178},"19":{"id":"2520-9-19","x":5965,"y":3800,"width":744,"height":178},"20":{"id":"2520-9-20","x":5965,"y":3978,"width":744,"height":180},"21":{"id":"2520-9-21","x":5965,"y":4158,"width":744,"height":175},"22":{"id":"2520-9-22","x":5965,"y":4333,"width":744,"height":11},"23":{"id":"2520-9-23","x":5965,"y":4357,"width":744,"height":551}}}}