{"image_id":"2549","document":"\u99ac\u82f1\u4e5d\/\u533f\u540d\u6350\u653f\/\u533f\u540d\u6350\u8d08.pdf","page_no":"0221","url":"img_orig\/072012a36840d0236cdfbe6c403f93b9-0221.jpg","width":"3510","height":"2482","cells":{"1":{"1":{"id":"2549-1-1","x":164,"y":249,"width":373,"height":91},"2":{"id":"2549-2-1","x":164,"y":335,"width":373,"height":93},"3":{"id":"2549-3-1","x":163,"y":422,"width":374,"height":97},"4":{"id":"2549-4-1","x":163,"y":514,"width":372,"height":93},"5":{"id":"2549-5-1","x":163,"y":601,"width":372,"height":93},"6":{"id":"2549-6-1","x":163,"y":689,"width":372,"height":93},"7":{"id":"2549-7-1","x":161,"y":777,"width":372,"height":93},"8":{"id":"2549-8-1","x":161,"y":865,"width":372,"height":93},"9":{"id":"2549-9-1","x":161,"y":952,"width":372,"height":95},"10":{"id":"2549-10-1","x":159,"y":1042,"width":374,"height":95},"11":{"id":"2549-11-1","x":159,"y":1131,"width":372,"height":93},"12":{"id":"2549-12-1","x":159,"y":1219,"width":372,"height":93},"13":{"id":"2549-13-1","x":159,"y":1307,"width":372,"height":93},"14":{"id":"2549-14-1","x":157,"y":1395,"width":374,"height":93},"15":{"id":"2549-15-1","x":157,"y":1482,"width":373,"height":93},"16":{"id":"2549-16-1","x":157,"y":1570,"width":373,"height":97},"17":{"id":"2549-17-1","x":157,"y":1661,"width":373,"height":94},"18":{"id":"2549-18-1","x":156,"y":1749,"width":374,"height":95},"19":{"id":"2549-19-1","x":156,"y":1839,"width":372,"height":93},"20":{"id":"2549-20-1","x":156,"y":1926,"width":372,"height":94},"21":{"id":"2549-21-1","x":156,"y":2014,"width":372,"height":100}},"2":{"1":{"id":"2549-1-2","x":537,"y":254,"width":201,"height":89},"2":{"id":"2549-2-2","x":537,"y":340,"width":200,"height":91},"3":{"id":"2549-3-2","x":537,"y":428,"width":200,"height":93},"4":{"id":"2549-4-2","x":537,"y":519,"width":198,"height":91},"5":{"id":"2549-5-2","x":535,"y":607,"width":198,"height":91},"6":{"id":"2549-6-2","x":535,"y":694,"width":198,"height":90},"7":{"id":"2549-7-2","x":535,"y":782,"width":196,"height":91},"8":{"id":"2549-8-2","x":533,"y":870,"width":198,"height":91},"9":{"id":"2549-9-2","x":533,"y":958,"width":197,"height":93},"10":{"id":"2549-10-2","x":533,"y":1047,"width":195,"height":93},"11":{"id":"2549-11-2","x":533,"y":1137,"width":195,"height":91},"12":{"id":"2549-12-2","x":531,"y":1224,"width":195,"height":90},"13":{"id":"2549-13-2","x":531,"y":1312,"width":195,"height":90},"14":{"id":"2549-14-2","x":531,"y":1400,"width":193,"height":89},"15":{"id":"2549-15-2","x":531,"y":1488,"width":192,"height":91},"16":{"id":"2549-16-2","x":530,"y":1575,"width":193,"height":94},"17":{"id":"2549-17-2","x":530,"y":1667,"width":191,"height":91},"18":{"id":"2549-18-2","x":530,"y":1755,"width":189,"height":93},"19":{"id":"2549-19-2","x":530,"y":1844,"width":189,"height":90},"20":{"id":"2549-20-2","x":528,"y":1932,"width":189,"height":89},"21":{"id":"2549-21-2","x":528,"y":2020,"width":189,"height":98}},"3":{"1":{"id":"2549-1-3","x":740,"y":256,"width":232,"height":91},"2":{"id":"2549-2-3","x":738,"y":343,"width":234,"height":92},"3":{"id":"2549-3-3","x":737,"y":431,"width":235,"height":93},"4":{"id":"2549-4-3","x":737,"y":521,"width":233,"height":93},"5":{"id":"2549-5-3","x":735,"y":610,"width":235,"height":92},"6":{"id":"2549-6-3","x":733,"y":698,"width":237,"height":89},"7":{"id":"2549-7-3","x":733,"y":784,"width":237,"height":93},"8":{"id":"2549-8-3","x":731,"y":873,"width":239,"height":92},"9":{"id":"2549-9-3","x":731,"y":961,"width":237,"height":93},"10":{"id":"2549-10-3","x":730,"y":1051,"width":238,"height":93},"11":{"id":"2549-11-3","x":728,"y":1140,"width":240,"height":92},"12":{"id":"2549-12-3","x":728,"y":1228,"width":240,"height":90},"13":{"id":"2549-13-3","x":726,"y":1314,"width":241,"height":91},"14":{"id":"2549-14-3","x":726,"y":1402,"width":241,"height":91},"15":{"id":"2549-15-3","x":724,"y":1489,"width":243,"height":94},"16":{"id":"2549-16-3","x":723,"y":1579,"width":244,"height":93},"17":{"id":"2549-17-3","x":723,"y":1669,"width":244,"height":93},"18":{"id":"2549-18-3","x":721,"y":1758,"width":244,"height":91},"19":{"id":"2549-19-3","x":719,"y":1848,"width":246,"height":89},"20":{"id":"2549-20-3","x":719,"y":1934,"width":246,"height":91},"21":{"id":"2549-21-3","x":717,"y":2021,"width":248,"height":100}},"4":{"1":{"id":"2549-1-4","x":972,"y":259,"width":242,"height":92},"2":{"id":"2549-2-4","x":972,"y":347,"width":242,"height":91},"3":{"id":"2549-3-4","x":972,"y":435,"width":242,"height":93},"4":{"id":"2549-4-4","x":972,"y":524,"width":240,"height":93},"5":{"id":"2549-5-4","x":970,"y":614,"width":242,"height":91},"6":{"id":"2549-6-4","x":970,"y":702,"width":240,"height":89},"7":{"id":"2549-7-4","x":970,"y":787,"width":240,"height":94},"8":{"id":"2549-8-4","x":970,"y":877,"width":240,"height":91},"9":{"id":"2549-9-4","x":970,"y":965,"width":239,"height":93},"10":{"id":"2549-10-4","x":968,"y":1054,"width":241,"height":93},"11":{"id":"2549-11-4","x":968,"y":1144,"width":239,"height":91},"12":{"id":"2549-12-4","x":968,"y":1232,"width":239,"height":89},"13":{"id":"2549-13-4","x":968,"y":1318,"width":239,"height":91},"14":{"id":"2549-14-4","x":967,"y":1405,"width":238,"height":92},"15":{"id":"2549-15-4","x":967,"y":1493,"width":238,"height":93},"16":{"id":"2549-16-4","x":967,"y":1583,"width":236,"height":93},"17":{"id":"2549-17-4","x":967,"y":1672,"width":236,"height":93},"18":{"id":"2549-18-4","x":967,"y":1762,"width":235,"height":91},"19":{"id":"2549-19-4","x":965,"y":1849,"width":237,"height":92},"20":{"id":"2549-20-4","x":965,"y":1937,"width":237,"height":91},"21":{"id":"2549-21-4","x":965,"y":2025,"width":235,"height":98}},"5":{"1":{"id":"2549-1-5","x":1216,"y":263,"width":338,"height":91},"2":{"id":"2549-2-5","x":1214,"y":351,"width":340,"height":91},"3":{"id":"2549-3-5","x":1214,"y":438,"width":339,"height":95},"4":{"id":"2549-4-5","x":1214,"y":528,"width":339,"height":93},"5":{"id":"2549-5-5","x":1212,"y":617,"width":341,"height":92},"6":{"id":"2549-6-5","x":1212,"y":705,"width":339,"height":91},"7":{"id":"2549-7-5","x":1210,"y":791,"width":341,"height":93},"8":{"id":"2549-8-5","x":1210,"y":881,"width":341,"height":91},"9":{"id":"2549-9-5","x":1210,"y":968,"width":339,"height":93},"10":{"id":"2549-10-5","x":1209,"y":1058,"width":340,"height":93},"11":{"id":"2549-11-5","x":1209,"y":1147,"width":340,"height":92},"12":{"id":"2549-12-5","x":1207,"y":1235,"width":342,"height":91},"13":{"id":"2549-13-5","x":1207,"y":1321,"width":340,"height":93},"14":{"id":"2549-14-5","x":1207,"y":1409,"width":340,"height":93},"15":{"id":"2549-15-5","x":1205,"y":1497,"width":342,"height":93},"16":{"id":"2549-16-5","x":1205,"y":1586,"width":341,"height":95},"17":{"id":"2549-17-5","x":1203,"y":1676,"width":343,"height":93},"18":{"id":"2549-18-5","x":1203,"y":1765,"width":343,"height":93},"19":{"id":"2549-19-5","x":1202,"y":1853,"width":342,"height":91},"20":{"id":"2549-20-5","x":1202,"y":1941,"width":342,"height":91},"21":{"id":"2549-21-5","x":1202,"y":2028,"width":342,"height":100}},"6":{"1":{"id":"2549-1-6","x":1554,"y":268,"width":936,"height":100},"2":{"id":"2549-2-6","x":1554,"y":354,"width":936,"height":102},"3":{"id":"2549-3-6","x":1554,"y":442,"width":934,"height":103},"4":{"id":"2549-4-6","x":1553,"y":533,"width":935,"height":102},"5":{"id":"2549-5-6","x":1553,"y":621,"width":933,"height":102},"6":{"id":"2549-6-6","x":1553,"y":709,"width":933,"height":100},"7":{"id":"2549-7-6","x":1551,"y":796,"width":934,"height":102},"8":{"id":"2549-8-6","x":1551,"y":884,"width":934,"height":102},"9":{"id":"2549-9-6","x":1551,"y":972,"width":932,"height":103},"10":{"id":"2549-10-6","x":1549,"y":1061,"width":934,"height":104},"11":{"id":"2549-11-6","x":1549,"y":1151,"width":932,"height":102},"12":{"id":"2549-12-6","x":1549,"y":1239,"width":932,"height":100},"13":{"id":"2549-13-6","x":1549,"y":1326,"width":930,"height":100},"14":{"id":"2549-14-6","x":1547,"y":1414,"width":932,"height":100},"15":{"id":"2549-15-6","x":1547,"y":1502,"width":931,"height":102},"16":{"id":"2549-16-6","x":1547,"y":1590,"width":931,"height":103},"17":{"id":"2549-17-6","x":1546,"y":1681,"width":930,"height":102},"18":{"id":"2549-18-6","x":1546,"y":1769,"width":928,"height":101},"19":{"id":"2549-19-6","x":1546,"y":1858,"width":928,"height":98},"20":{"id":"2549-20-6","x":1544,"y":1944,"width":928,"height":100},"21":{"id":"2549-21-6","x":1544,"y":2032,"width":928,"height":107}},"7":{"1":{"id":"2549-1-7","x":2492,"y":280,"width":424,"height":93},"2":{"id":"2549-2-7","x":2490,"y":368,"width":426,"height":93},"3":{"id":"2549-3-7","x":2490,"y":456,"width":426,"height":96},"4":{"id":"2549-4-7","x":2488,"y":545,"width":428,"height":95},"5":{"id":"2549-5-7","x":2488,"y":635,"width":428,"height":93},"6":{"id":"2549-6-7","x":2486,"y":723,"width":430,"height":93},"7":{"id":"2549-7-7","x":2486,"y":809,"width":430,"height":94},"8":{"id":"2549-8-7","x":2485,"y":898,"width":431,"height":93},"9":{"id":"2549-9-7","x":2485,"y":986,"width":431,"height":95},"10":{"id":"2549-10-7","x":2483,"y":1075,"width":433,"height":95},"11":{"id":"2549-11-7","x":2483,"y":1165,"width":432,"height":93},"12":{"id":"2549-12-7","x":2481,"y":1253,"width":434,"height":93},"13":{"id":"2549-13-7","x":2481,"y":1339,"width":434,"height":94},"14":{"id":"2549-14-7","x":2479,"y":1426,"width":436,"height":95},"15":{"id":"2549-15-7","x":2479,"y":1514,"width":436,"height":95},"16":{"id":"2549-16-7","x":2478,"y":1604,"width":437,"height":96},"17":{"id":"2549-17-7","x":2478,"y":1693,"width":437,"height":95},"18":{"id":"2549-18-7","x":2476,"y":1783,"width":439,"height":93},"19":{"id":"2549-19-7","x":2474,"y":1870,"width":441,"height":92},"20":{"id":"2549-20-7","x":2474,"y":1956,"width":441,"height":93},"21":{"id":"2549-21-7","x":2472,"y":2044,"width":443,"height":100}},"8":{"1":{"id":"2549-1-8","x":2916,"y":287,"width":286,"height":92},"2":{"id":"2549-2-8","x":2916,"y":373,"width":286,"height":93},"3":{"id":"2549-3-8","x":2916,"y":461,"width":286,"height":95},"4":{"id":"2549-4-8","x":2916,"y":552,"width":286,"height":93},"5":{"id":"2549-5-8","x":2916,"y":640,"width":286,"height":93},"6":{"id":"2549-6-8","x":2916,"y":728,"width":286,"height":91},"7":{"id":"2549-7-8","x":2916,"y":816,"width":286,"height":93},"8":{"id":"2549-8-8","x":2916,"y":903,"width":286,"height":93},"9":{"id":"2549-9-8","x":2916,"y":991,"width":286,"height":95},"10":{"id":"2549-10-8","x":2916,"y":1081,"width":286,"height":94},"11":{"id":"2549-11-8","x":2916,"y":1170,"width":286,"height":93},"12":{"id":"2549-12-8","x":2915,"y":1258,"width":287,"height":91},"13":{"id":"2549-13-8","x":2915,"y":1346,"width":287,"height":91},"14":{"id":"2549-14-8","x":2915,"y":1433,"width":287,"height":92},"15":{"id":"2549-15-8","x":2915,"y":1521,"width":287,"height":93},"16":{"id":"2549-16-8","x":2915,"y":1609,"width":287,"height":95},"17":{"id":"2549-17-8","x":2915,"y":1700,"width":287,"height":93},"18":{"id":"2549-18-8","x":2915,"y":1788,"width":287,"height":93},"19":{"id":"2549-19-8","x":2915,"y":1876,"width":287,"height":89},"20":{"id":"2549-20-8","x":2915,"y":1962,"width":287,"height":91},"21":{"id":"2549-21-8","x":2915,"y":2049,"width":287,"height":99}},"9":{"1":{"id":"2549-1-9","x":3202,"y":291,"width":172,"height":89},"2":{"id":"2549-2-9","x":3202,"y":379,"width":172,"height":89},"3":{"id":"2549-3-9","x":3202,"y":466,"width":172,"height":92},"4":{"id":"2549-4-9","x":3202,"y":556,"width":171,"height":91},"5":{"id":"2549-5-9","x":3202,"y":645,"width":171,"height":90},"6":{"id":"2549-6-9","x":3202,"y":733,"width":171,"height":88},"7":{"id":"2549-7-9","x":3202,"y":819,"width":171,"height":91},"8":{"id":"2549-8-9","x":3202,"y":909,"width":169,"height":89},"9":{"id":"2549-9-9","x":3202,"y":996,"width":169,"height":92},"10":{"id":"2549-10-9","x":3202,"y":1086,"width":169,"height":91},"11":{"id":"2549-11-9","x":3202,"y":1175,"width":167,"height":90},"12":{"id":"2549-12-9","x":3202,"y":1263,"width":167,"height":88},"13":{"id":"2549-13-9","x":3202,"y":1349,"width":167,"height":90},"14":{"id":"2549-14-9","x":3202,"y":1437,"width":165,"height":89},"15":{"id":"2549-15-9","x":3202,"y":1525,"width":165,"height":91},"16":{"id":"2549-16-9","x":3202,"y":1614,"width":165,"height":91},"17":{"id":"2549-17-9","x":3202,"y":1704,"width":164,"height":91},"18":{"id":"2549-18-9","x":3202,"y":1793,"width":164,"height":90},"19":{"id":"2549-19-9","x":3202,"y":1881,"width":164,"height":86},"20":{"id":"2549-20-9","x":3202,"y":1965,"width":162,"height":90},"21":{"id":"2549-21-9","x":3202,"y":2053,"width":162,"height":96}}},"cellCount":189}