{"image_id":"326","document":"\u5f90\u8000\u660c\/\u96c6\u6703\u652f\u51fa\/\u96c6\u6703\u652f\u51fa.pdf","page_no":"0003","url":"img_orig\/3ea9ed17d7589003014de0f6298e80e7-0003.jpg","width":"3539","height":"2524","cells":{"1":{"1":{"id":"326-1-1","x":184,"y":350,"width":169,"height":95},"2":{"id":"326-2-1","x":184,"y":445,"width":169,"height":91},"3":{"id":"326-3-1","x":184,"y":534,"width":169,"height":90},"4":{"id":"326-4-1","x":184,"y":624,"width":169,"height":90},"5":{"id":"326-5-1","x":184,"y":713,"width":169,"height":90},"6":{"id":"326-6-1","x":184,"y":801,"width":169,"height":92},"7":{"id":"326-7-1","x":184,"y":891,"width":169,"height":89},"8":{"id":"326-8-1","x":184,"y":980,"width":169,"height":90},"9":{"id":"326-9-1","x":184,"y":1070,"width":169,"height":87},"10":{"id":"326-10-1","x":184,"y":1157,"width":169,"height":92},"11":{"id":"326-11-1","x":184,"y":1247,"width":169,"height":87},"12":{"id":"326-12-1","x":185,"y":1334,"width":168,"height":88},"13":{"id":"326-13-1","x":185,"y":1422,"width":168,"height":90},"14":{"id":"326-14-1","x":185,"y":1511,"width":168,"height":90},"15":{"id":"326-15-1","x":185,"y":1601,"width":168,"height":88},"16":{"id":"326-16-1","x":185,"y":1689,"width":168,"height":91},"17":{"id":"326-17-1","x":185,"y":1780,"width":168,"height":90},"18":{"id":"326-18-1","x":185,"y":1870,"width":168,"height":88},"19":{"id":"326-19-1","x":185,"y":1958,"width":168,"height":89},"20":{"id":"326-20-1","x":185,"y":2047,"width":168,"height":87},"21":{"id":"326-21-1","x":185,"y":2132,"width":168,"height":92}},"2":{"1":{"id":"326-1-2","x":353,"y":350,"width":291,"height":97},"2":{"id":"326-2-2","x":353,"y":445,"width":291,"height":92},"3":{"id":"326-3-2","x":353,"y":536,"width":291,"height":90},"4":{"id":"326-4-2","x":353,"y":624,"width":291,"height":92},"5":{"id":"326-5-2","x":353,"y":714,"width":291,"height":91},"6":{"id":"326-6-2","x":353,"y":803,"width":291,"height":90},"7":{"id":"326-7-2","x":353,"y":893,"width":291,"height":89},"8":{"id":"326-8-2","x":353,"y":980,"width":291,"height":92},"9":{"id":"326-9-2","x":353,"y":1070,"width":291,"height":89},"10":{"id":"326-10-2","x":353,"y":1157,"width":291,"height":92},"11":{"id":"326-11-2","x":353,"y":1249,"width":291,"height":86},"12":{"id":"326-12-2","x":353,"y":1334,"width":291,"height":90},"13":{"id":"326-13-2","x":353,"y":1422,"width":291,"height":90},"14":{"id":"326-14-2","x":353,"y":1512,"width":291,"height":91},"15":{"id":"326-15-2","x":353,"y":1601,"width":291,"height":90},"16":{"id":"326-16-2","x":353,"y":1689,"width":291,"height":91},"17":{"id":"326-17-2","x":353,"y":1780,"width":291,"height":90},"18":{"id":"326-18-2","x":353,"y":1870,"width":291,"height":88},"19":{"id":"326-19-2","x":353,"y":1958,"width":291,"height":89},"20":{"id":"326-20-2","x":353,"y":2047,"width":291,"height":87},"21":{"id":"326-21-2","x":353,"y":2134,"width":291,"height":90}},"3":{"1":{"id":"326-1-3","x":644,"y":352,"width":435,"height":97},"2":{"id":"326-2-3","x":644,"y":447,"width":435,"height":92},"3":{"id":"326-3-3","x":644,"y":537,"width":435,"height":91},"4":{"id":"326-4-3","x":644,"y":626,"width":435,"height":92},"5":{"id":"326-5-3","x":644,"y":716,"width":435,"height":90},"6":{"id":"326-6-3","x":644,"y":805,"width":435,"height":90},"7":{"id":"326-7-3","x":644,"y":893,"width":435,"height":90},"8":{"id":"326-8-3","x":644,"y":982,"width":435,"height":90},"9":{"id":"326-9-3","x":644,"y":1072,"width":435,"height":88},"10":{"id":"326-10-3","x":644,"y":1159,"width":435,"height":92},"11":{"id":"326-11-3","x":644,"y":1249,"width":435,"height":88},"12":{"id":"326-12-3","x":644,"y":1335,"width":435,"height":91},"13":{"id":"326-13-3","x":644,"y":1424,"width":435,"height":90},"14":{"id":"326-14-3","x":644,"y":1512,"width":435,"height":92},"15":{"id":"326-15-3","x":644,"y":1603,"width":435,"height":90},"16":{"id":"326-16-3","x":644,"y":1691,"width":435,"height":90},"17":{"id":"326-17-3","x":644,"y":1780,"width":435,"height":92},"18":{"id":"326-18-3","x":644,"y":1870,"width":435,"height":90},"19":{"id":"326-19-3","x":644,"y":1958,"width":435,"height":91},"20":{"id":"326-20-3","x":644,"y":2047,"width":435,"height":87},"21":{"id":"326-21-3","x":644,"y":2134,"width":435,"height":90}},"4":{"1":{"id":"326-1-4","x":1079,"y":353,"width":932,"height":101},"2":{"id":"326-2-4","x":1079,"y":449,"width":932,"height":96},"3":{"id":"326-3-4","x":1079,"y":539,"width":932,"height":94},"4":{"id":"326-4-4","x":1079,"y":628,"width":932,"height":95},"5":{"id":"326-5-4","x":1079,"y":718,"width":932,"height":94},"6":{"id":"326-6-4","x":1079,"y":806,"width":932,"height":92},"7":{"id":"326-7-4","x":1079,"y":895,"width":932,"height":90},"8":{"id":"326-8-4","x":1079,"y":983,"width":932,"height":92},"9":{"id":"326-9-4","x":1079,"y":1072,"width":932,"height":92},"10":{"id":"326-10-4","x":1079,"y":1160,"width":932,"height":92},"11":{"id":"326-11-4","x":1079,"y":1251,"width":934,"height":88},"12":{"id":"326-12-4","x":1079,"y":1337,"width":934,"height":90},"13":{"id":"326-13-4","x":1079,"y":1426,"width":934,"height":92},"14":{"id":"326-14-4","x":1079,"y":1514,"width":934,"height":92},"15":{"id":"326-15-4","x":1079,"y":1604,"width":934,"height":91},"16":{"id":"326-16-4","x":1079,"y":1693,"width":934,"height":90},"17":{"id":"326-17-4","x":1079,"y":1781,"width":934,"height":92},"18":{"id":"326-18-4","x":1079,"y":1872,"width":934,"height":90},"19":{"id":"326-19-4","x":1079,"y":1960,"width":934,"height":90},"20":{"id":"326-20-4","x":1079,"y":2049,"width":934,"height":86},"21":{"id":"326-21-4","x":1079,"y":2134,"width":934,"height":92}},"5":{"1":{"id":"326-1-5","x":2011,"y":359,"width":340,"height":97},"2":{"id":"326-2-5","x":2011,"y":454,"width":340,"height":92},"3":{"id":"326-3-5","x":2011,"y":545,"width":340,"height":90},"4":{"id":"326-4-5","x":2011,"y":633,"width":340,"height":92},"5":{"id":"326-5-5","x":2011,"y":723,"width":340,"height":90},"6":{"id":"326-6-5","x":2011,"y":812,"width":340,"height":88},"7":{"id":"326-7-5","x":2011,"y":898,"width":340,"height":89},"8":{"id":"326-8-5","x":2011,"y":985,"width":340,"height":90},"9":{"id":"326-9-5","x":2011,"y":1075,"width":340,"height":91},"10":{"id":"326-10-5","x":2011,"y":1164,"width":340,"height":88},"11":{"id":"326-11-5","x":2011,"y":1252,"width":340,"height":89},"12":{"id":"326-12-5","x":2013,"y":1339,"width":338,"height":90},"13":{"id":"326-13-5","x":2013,"y":1427,"width":338,"height":93},"14":{"id":"326-14-5","x":2013,"y":1518,"width":338,"height":90},"15":{"id":"326-15-5","x":2013,"y":1606,"width":338,"height":90},"16":{"id":"326-16-5","x":2013,"y":1695,"width":338,"height":88},"17":{"id":"326-17-5","x":2013,"y":1783,"width":338,"height":90},"18":{"id":"326-18-5","x":2013,"y":1873,"width":338,"height":89},"19":{"id":"326-19-5","x":2013,"y":1962,"width":338,"height":88},"20":{"id":"326-20-5","x":2013,"y":2050,"width":338,"height":87},"21":{"id":"326-21-5","x":2013,"y":2135,"width":338,"height":92}},"6":{"1":{"id":"326-1-6","x":2351,"y":360,"width":246,"height":98},"2":{"id":"326-2-6","x":2351,"y":456,"width":244,"height":90},"3":{"id":"326-3-6","x":2351,"y":546,"width":244,"height":91},"4":{"id":"326-4-6","x":2351,"y":635,"width":244,"height":90},"5":{"id":"326-5-6","x":2351,"y":725,"width":244,"height":88},"6":{"id":"326-6-6","x":2351,"y":813,"width":244,"height":87},"7":{"id":"326-7-6","x":2351,"y":900,"width":243,"height":89},"8":{"id":"326-8-6","x":2351,"y":987,"width":243,"height":90},"9":{"id":"326-9-6","x":2351,"y":1075,"width":243,"height":91},"10":{"id":"326-10-6","x":2351,"y":1166,"width":243,"height":88},"11":{"id":"326-11-6","x":2351,"y":1252,"width":241,"height":91},"12":{"id":"326-12-6","x":2351,"y":1341,"width":241,"height":90},"13":{"id":"326-13-6","x":2351,"y":1429,"width":241,"height":91},"14":{"id":"326-14-6","x":2351,"y":1520,"width":241,"height":90},"15":{"id":"326-15-6","x":2351,"y":1608,"width":239,"height":90},"16":{"id":"326-16-6","x":2351,"y":1696,"width":239,"height":87},"17":{"id":"326-17-6","x":2351,"y":1783,"width":239,"height":90},"18":{"id":"326-18-6","x":2351,"y":1873,"width":239,"height":89},"19":{"id":"326-19-6","x":2351,"y":1962,"width":239,"height":88},"20":{"id":"326-20-6","x":2351,"y":2050,"width":237,"height":87},"21":{"id":"326-21-6","x":2351,"y":2137,"width":237,"height":90}},"7":{"1":{"id":"326-1-7","x":2597,"y":362,"width":234,"height":98},"2":{"id":"326-2-7","x":2597,"y":458,"width":234,"height":90},"3":{"id":"326-3-7","x":2595,"y":546,"width":236,"height":92},"4":{"id":"326-4-7","x":2595,"y":637,"width":236,"height":90},"5":{"id":"326-5-7","x":2595,"y":725,"width":236,"height":90},"6":{"id":"326-6-7","x":2595,"y":813,"width":236,"height":89},"7":{"id":"326-7-7","x":2595,"y":900,"width":236,"height":89},"8":{"id":"326-8-7","x":2594,"y":989,"width":237,"height":88},"9":{"id":"326-9-7","x":2594,"y":1077,"width":237,"height":90},"10":{"id":"326-10-7","x":2594,"y":1166,"width":237,"height":88},"11":{"id":"326-11-7","x":2594,"y":1254,"width":237,"height":89},"12":{"id":"326-12-7","x":2592,"y":1343,"width":239,"height":88},"13":{"id":"326-13-7","x":2592,"y":1431,"width":239,"height":90},"14":{"id":"326-14-7","x":2592,"y":1520,"width":239,"height":90},"15":{"id":"326-15-7","x":2592,"y":1610,"width":239,"height":88},"16":{"id":"326-16-7","x":2590,"y":1698,"width":241,"height":87},"17":{"id":"326-17-7","x":2590,"y":1783,"width":241,"height":92},"18":{"id":"326-18-7","x":2590,"y":1873,"width":241,"height":91},"19":{"id":"326-19-7","x":2590,"y":1962,"width":241,"height":90},"20":{"id":"326-20-7","x":2590,"y":2050,"width":241,"height":87},"21":{"id":"326-21-7","x":2588,"y":2137,"width":243,"height":90}},"8":{"1":{"id":"326-1-8","x":2831,"y":364,"width":196,"height":96},"2":{"id":"326-2-8","x":2831,"y":460,"width":196,"height":90},"3":{"id":"326-3-8","x":2831,"y":548,"width":196,"height":90},"4":{"id":"326-4-8","x":2831,"y":638,"width":196,"height":91},"5":{"id":"326-5-8","x":2831,"y":727,"width":196,"height":90},"6":{"id":"326-6-8","x":2831,"y":815,"width":196,"height":87},"7":{"id":"326-7-8","x":2831,"y":902,"width":196,"height":87},"8":{"id":"326-8-8","x":2831,"y":989,"width":196,"height":90},"9":{"id":"326-9-8","x":2831,"y":1077,"width":196,"height":90},"10":{"id":"326-10-8","x":2831,"y":1167,"width":196,"height":87},"11":{"id":"326-11-8","x":2831,"y":1254,"width":196,"height":89},"12":{"id":"326-12-8","x":2831,"y":1343,"width":196,"height":88},"13":{"id":"326-13-8","x":2831,"y":1431,"width":196,"height":90},"14":{"id":"326-14-8","x":2831,"y":1521,"width":196,"height":89},"15":{"id":"326-15-8","x":2831,"y":1610,"width":196,"height":88},"16":{"id":"326-16-8","x":2831,"y":1698,"width":196,"height":87},"17":{"id":"326-17-8","x":2831,"y":1785,"width":196,"height":90},"18":{"id":"326-18-8","x":2831,"y":1875,"width":196,"height":89},"19":{"id":"326-19-8","x":2831,"y":1964,"width":196,"height":88},"20":{"id":"326-20-8","x":2831,"y":2052,"width":196,"height":85},"21":{"id":"326-21-8","x":2831,"y":2137,"width":196,"height":90}},"9":{"1":{"id":"326-1-9","x":3027,"y":364,"width":372,"height":97},"2":{"id":"326-2-9","x":3027,"y":460,"width":372,"height":92},"3":{"id":"326-3-9","x":3027,"y":550,"width":372,"height":90},"4":{"id":"326-4-9","x":3027,"y":638,"width":372,"height":92},"5":{"id":"326-5-9","x":3027,"y":729,"width":372,"height":90},"6":{"id":"326-6-9","x":3027,"y":817,"width":372,"height":87},"7":{"id":"326-7-9","x":3027,"y":902,"width":372,"height":88},"8":{"id":"326-8-9","x":3027,"y":989,"width":372,"height":90},"9":{"id":"326-9-9","x":3027,"y":1079,"width":372,"height":90},"10":{"id":"326-10-9","x":3027,"y":1167,"width":372,"height":89},"11":{"id":"326-11-9","x":3027,"y":1254,"width":372,"height":90},"12":{"id":"326-12-9","x":3027,"y":1343,"width":372,"height":90},"13":{"id":"326-13-9","x":3027,"y":1431,"width":372,"height":92},"14":{"id":"326-14-9","x":3027,"y":1521,"width":372,"height":91},"15":{"id":"326-15-9","x":3027,"y":1610,"width":372,"height":90},"16":{"id":"326-16-9","x":3027,"y":1698,"width":372,"height":87},"17":{"id":"326-17-9","x":3027,"y":1785,"width":372,"height":90},"18":{"id":"326-18-9","x":3027,"y":1875,"width":372,"height":89},"19":{"id":"326-19-9","x":3027,"y":1964,"width":372,"height":88},"20":{"id":"326-20-9","x":3027,"y":2052,"width":372,"height":87},"21":{"id":"326-21-9","x":3027,"y":2137,"width":372,"height":92}}},"cellCount":189}