{"image_id":"397","document":"\u99ac\u82f1\u4e5d\/\u96c6\u6703\u652f\u51fa\/img-220095631.pdf","page_no":"193","url":"http:\/\/pic.pimg.tw\/ronnywang\/1393536100-2448794155.jpg?v=1393536105","width":"7020","height":"4964","cells":{"1":{"1":{"id":"397-1-1","x":256,"y":694,"width":333,"height":197},"2":{"id":"397-1-2","x":256,"y":888,"width":333,"height":179},"3":{"id":"397-1-3","x":256,"y":1063,"width":333,"height":176},"4":{"id":"397-1-4","x":256,"y":1235,"width":333,"height":172},"5":{"id":"397-1-5","x":256,"y":1407,"width":333,"height":179},"6":{"id":"397-1-6","x":256,"y":1583,"width":333,"height":179},"7":{"id":"397-1-7","x":256,"y":1762,"width":333,"height":175},"8":{"id":"397-1-8","x":256,"y":1934,"width":333,"height":179},"9":{"id":"397-1-9","x":256,"y":2109,"width":333,"height":179},"10":{"id":"397-1-10","x":256,"y":2285,"width":333,"height":179},"11":{"id":"397-1-11","x":256,"y":2460,"width":330,"height":183},"12":{"id":"397-1-12","x":252,"y":2639,"width":334,"height":176},"13":{"id":"397-1-13","x":252,"y":2811,"width":334,"height":179},"14":{"id":"397-1-14","x":252,"y":2987,"width":334,"height":175},"15":{"id":"397-1-15","x":252,"y":3159,"width":334,"height":175},"16":{"id":"397-1-16","x":252,"y":3334,"width":334,"height":176},"17":{"id":"397-1-17","x":252,"y":3510,"width":334,"height":175},"18":{"id":"397-1-18","x":252,"y":3681,"width":334,"height":179},"19":{"id":"397-1-19","x":252,"y":3860,"width":334,"height":176},"20":{"id":"397-1-20","x":252,"y":4032,"width":334,"height":180},"21":{"id":"397-1-21","x":252,"y":4208,"width":334,"height":179}},"2":{"1":{"id":"397-2-1","x":589,"y":694,"width":576,"height":197},"2":{"id":"397-2-2","x":589,"y":891,"width":576,"height":176},"3":{"id":"397-2-3","x":589,"y":1067,"width":576,"height":172},"4":{"id":"397-2-4","x":589,"y":1239,"width":576,"height":172},"5":{"id":"397-2-5","x":589,"y":1407,"width":576,"height":179},"6":{"id":"397-2-6","x":589,"y":1586,"width":576,"height":179},"7":{"id":"397-2-7","x":589,"y":1762,"width":576,"height":175},"8":{"id":"397-2-8","x":589,"y":1937,"width":576,"height":176},"9":{"id":"397-2-9","x":589,"y":2113,"width":576,"height":175},"10":{"id":"397-2-10","x":589,"y":2288,"width":576,"height":176},"11":{"id":"397-2-11","x":589,"y":2464,"width":572,"height":179},"12":{"id":"397-2-12","x":586,"y":2643,"width":575,"height":172},"13":{"id":"397-2-13","x":586,"y":2815,"width":575,"height":175},"14":{"id":"397-2-14","x":586,"y":2990,"width":575,"height":172},"15":{"id":"397-2-15","x":586,"y":3162,"width":575,"height":176},"16":{"id":"397-2-16","x":586,"y":3334,"width":575,"height":179},"17":{"id":"397-2-17","x":586,"y":3510,"width":575,"height":175},"18":{"id":"397-2-18","x":586,"y":3685,"width":575,"height":179},"19":{"id":"397-2-19","x":586,"y":3860,"width":575,"height":176},"20":{"id":"397-2-20","x":586,"y":4036,"width":575,"height":176},"21":{"id":"397-2-21","x":586,"y":4212,"width":575,"height":175}},"3":{"1":{"id":"397-3-1","x":1165,"y":698,"width":863,"height":197},"2":{"id":"397-3-2","x":1165,"y":891,"width":863,"height":179},"3":{"id":"397-3-3","x":1165,"y":1067,"width":863,"height":175},"4":{"id":"397-3-4","x":1165,"y":1239,"width":863,"height":175},"5":{"id":"397-3-5","x":1165,"y":1411,"width":863,"height":179},"6":{"id":"397-3-6","x":1165,"y":1586,"width":863,"height":183},"7":{"id":"397-3-7","x":1165,"y":1765,"width":863,"height":176},"8":{"id":"397-3-8","x":1165,"y":1937,"width":863,"height":179},"9":{"id":"397-3-9","x":1165,"y":2113,"width":863,"height":179},"10":{"id":"397-3-10","x":1165,"y":2288,"width":863,"height":179},"11":{"id":"397-3-11","x":1165,"y":2464,"width":860,"height":182},"12":{"id":"397-3-12","x":1161,"y":2643,"width":864,"height":175},"13":{"id":"397-3-13","x":1161,"y":2815,"width":864,"height":179},"14":{"id":"397-3-14","x":1161,"y":2990,"width":864,"height":176},"15":{"id":"397-3-15","x":1161,"y":3162,"width":864,"height":179},"16":{"id":"397-3-16","x":1161,"y":3338,"width":864,"height":179},"17":{"id":"397-3-17","x":1161,"y":3513,"width":864,"height":176},"18":{"id":"397-3-18","x":1161,"y":3685,"width":864,"height":183},"19":{"id":"397-3-19","x":1161,"y":3864,"width":864,"height":176},"20":{"id":"397-3-20","x":1161,"y":4036,"width":864,"height":179},"21":{"id":"397-3-21","x":1161,"y":4212,"width":864,"height":179}},"4":{"1":{"id":"397-4-1","x":2028,"y":702,"width":1857,"height":200},"2":{"id":"397-4-2","x":2028,"y":895,"width":1857,"height":182},"3":{"id":"397-4-3","x":2028,"y":1070,"width":1857,"height":179},"4":{"id":"397-4-4","x":2028,"y":1242,"width":1857,"height":176},"5":{"id":"397-4-5","x":2028,"y":1414,"width":1857,"height":183},"6":{"id":"397-4-6","x":2028,"y":1590,"width":1857,"height":182},"7":{"id":"397-4-7","x":2028,"y":1769,"width":1857,"height":179},"8":{"id":"397-4-8","x":2028,"y":1941,"width":1857,"height":182},"9":{"id":"397-4-9","x":2028,"y":2116,"width":1857,"height":183},"10":{"id":"397-4-10","x":2028,"y":2292,"width":1857,"height":182},"11":{"id":"397-4-11","x":2028,"y":2467,"width":1857,"height":186},"12":{"id":"397-4-12","x":2025,"y":2646,"width":1860,"height":179},"13":{"id":"397-4-13","x":2025,"y":2818,"width":1860,"height":183},"14":{"id":"397-4-14","x":2025,"y":2994,"width":1860,"height":179},"15":{"id":"397-4-15","x":2025,"y":3166,"width":1860,"height":179},"16":{"id":"397-4-16","x":2025,"y":3341,"width":1860,"height":179},"17":{"id":"397-4-17","x":2025,"y":3517,"width":1860,"height":179},"18":{"id":"397-4-18","x":2025,"y":3689,"width":1860,"height":182},"19":{"id":"397-4-19","x":2025,"y":3868,"width":1860,"height":179},"20":{"id":"397-4-20","x":2025,"y":4040,"width":1860,"height":182},"21":{"id":"397-4-21","x":2025,"y":4215,"width":1860,"height":183}},"5":{"1":{"id":"397-5-1","x":3885,"y":705,"width":678,"height":200},"2":{"id":"397-5-2","x":3885,"y":902,"width":678,"height":179},"3":{"id":"397-5-3","x":3885,"y":1077,"width":678,"height":176},"4":{"id":"397-5-4","x":3885,"y":1249,"width":678,"height":172},"5":{"id":"397-5-5","x":3885,"y":1418,"width":678,"height":182},"6":{"id":"397-5-6","x":3885,"y":1597,"width":678,"height":179},"7":{"id":"397-5-7","x":3885,"y":1772,"width":678,"height":179},"8":{"id":"397-5-8","x":3885,"y":1948,"width":678,"height":179},"9":{"id":"397-5-9","x":3885,"y":2123,"width":678,"height":179},"10":{"id":"397-5-10","x":3885,"y":2299,"width":678,"height":179},"11":{"id":"397-5-11","x":3885,"y":2474,"width":678,"height":183},"12":{"id":"397-5-12","x":3885,"y":2653,"width":678,"height":176},"13":{"id":"397-5-13","x":3885,"y":2825,"width":678,"height":179},"14":{"id":"397-5-14","x":3885,"y":3001,"width":678,"height":175},"15":{"id":"397-5-15","x":3885,"y":3173,"width":678,"height":175},"16":{"id":"397-5-16","x":3885,"y":3345,"width":678,"height":179},"17":{"id":"397-5-17","x":3885,"y":3520,"width":678,"height":179},"18":{"id":"397-5-18","x":3885,"y":3696,"width":678,"height":179},"19":{"id":"397-5-19","x":3885,"y":3871,"width":678,"height":179},"20":{"id":"397-5-20","x":3885,"y":4047,"width":678,"height":179},"21":{"id":"397-5-21","x":3885,"y":4222,"width":678,"height":179}},"6":{"1":{"id":"397-6-1","x":4563,"y":709,"width":477,"height":196},"2":{"id":"397-6-2","x":4563,"y":905,"width":477,"height":176},"3":{"id":"397-6-3","x":4563,"y":1081,"width":477,"height":172},"4":{"id":"397-6-4","x":4563,"y":1253,"width":477,"height":172},"5":{"id":"397-6-5","x":4563,"y":1421,"width":477,"height":179},"6":{"id":"397-6-6","x":4563,"y":1600,"width":477,"height":179},"7":{"id":"397-6-7","x":4563,"y":1776,"width":477,"height":175},"8":{"id":"397-6-8","x":4563,"y":1951,"width":477,"height":176},"9":{"id":"397-6-9","x":4563,"y":2127,"width":477,"height":175},"10":{"id":"397-6-10","x":4563,"y":2302,"width":477,"height":176},"11":{"id":"397-6-11","x":4563,"y":2478,"width":480,"height":179},"12":{"id":"397-6-12","x":4563,"y":2657,"width":480,"height":172},"13":{"id":"397-6-13","x":4563,"y":2829,"width":480,"height":175},"14":{"id":"397-6-14","x":4563,"y":3004,"width":480,"height":172},"15":{"id":"397-6-15","x":4563,"y":3176,"width":480,"height":176},"16":{"id":"397-6-16","x":4563,"y":3348,"width":480,"height":179},"17":{"id":"397-6-17","x":4563,"y":3524,"width":480,"height":175},"18":{"id":"397-6-18","x":4563,"y":3699,"width":480,"height":179},"19":{"id":"397-6-19","x":4563,"y":3875,"width":480,"height":175},"20":{"id":"397-6-20","x":4563,"y":4050,"width":480,"height":176},"21":{"id":"397-6-21","x":4563,"y":4226,"width":480,"height":175}},"7":{"1":{"id":"397-7-1","x":5040,"y":712,"width":481,"height":197},"2":{"id":"397-7-2","x":5040,"y":905,"width":481,"height":179},"3":{"id":"397-7-3","x":5040,"y":1081,"width":481,"height":175},"4":{"id":"397-7-4","x":5040,"y":1253,"width":481,"height":172},"5":{"id":"397-7-5","x":5040,"y":1425,"width":481,"height":179},"6":{"id":"397-7-6","x":5040,"y":1600,"width":481,"height":179},"7":{"id":"397-7-7","x":5040,"y":1779,"width":481,"height":176},"8":{"id":"397-7-8","x":5040,"y":1951,"width":481,"height":179},"9":{"id":"397-7-9","x":5040,"y":2127,"width":481,"height":179},"10":{"id":"397-7-10","x":5040,"y":2302,"width":481,"height":179},"11":{"id":"397-7-11","x":5040,"y":2478,"width":477,"height":182},"12":{"id":"397-7-12","x":5043,"y":2657,"width":474,"height":172},"13":{"id":"397-7-13","x":5043,"y":2829,"width":474,"height":175},"14":{"id":"397-7-14","x":5043,"y":3004,"width":474,"height":172},"15":{"id":"397-7-15","x":5043,"y":3176,"width":474,"height":176},"16":{"id":"397-7-16","x":5043,"y":3352,"width":474,"height":175},"17":{"id":"397-7-17","x":5043,"y":3527,"width":474,"height":172},"18":{"id":"397-7-18","x":5043,"y":3699,"width":474,"height":179},"19":{"id":"397-7-19","x":5043,"y":3878,"width":474,"height":172},"20":{"id":"397-7-20","x":5043,"y":4050,"width":474,"height":176},"21":{"id":"397-7-21","x":5043,"y":4226,"width":474,"height":175}},"8":{"1":{"id":"397-8-1","x":5521,"y":712,"width":393,"height":197},"2":{"id":"397-8-2","x":5521,"y":909,"width":393,"height":175},"3":{"id":"397-8-3","x":5521,"y":1084,"width":393,"height":172},"4":{"id":"397-8-4","x":5521,"y":1256,"width":393,"height":169},"5":{"id":"397-8-5","x":5521,"y":1425,"width":393,"height":179},"6":{"id":"397-8-6","x":5521,"y":1604,"width":393,"height":175},"7":{"id":"397-8-7","x":5521,"y":1779,"width":393,"height":176},"8":{"id":"397-8-8","x":5521,"y":1955,"width":393,"height":175},"9":{"id":"397-8-9","x":5521,"y":2130,"width":393,"height":176},"10":{"id":"397-8-10","x":5521,"y":2306,"width":393,"height":175},"11":{"id":"397-8-11","x":5521,"y":2481,"width":389,"height":179},"12":{"id":"397-8-12","x":5517,"y":2660,"width":393,"height":172},"13":{"id":"397-8-13","x":5517,"y":2829,"width":393,"height":179},"14":{"id":"397-8-14","x":5517,"y":3004,"width":393,"height":176},"15":{"id":"397-8-15","x":5517,"y":3176,"width":393,"height":176},"16":{"id":"397-8-16","x":5517,"y":3352,"width":393,"height":175},"17":{"id":"397-8-17","x":5517,"y":3527,"width":393,"height":176},"18":{"id":"397-8-18","x":5517,"y":3699,"width":393,"height":179},"19":{"id":"397-8-19","x":5517,"y":3878,"width":393,"height":176},"20":{"id":"397-8-20","x":5517,"y":4050,"width":393,"height":179},"21":{"id":"397-8-21","x":5517,"y":4226,"width":393,"height":179}},"9":{"1":{"id":"397-9-1","x":5914,"y":712,"width":740,"height":200},"2":{"id":"397-9-2","x":5914,"y":909,"width":740,"height":179},"3":{"id":"397-9-3","x":5914,"y":1084,"width":740,"height":176},"4":{"id":"397-9-4","x":5914,"y":1256,"width":740,"height":172},"5":{"id":"397-9-5","x":5914,"y":1425,"width":740,"height":182},"6":{"id":"397-9-6","x":5914,"y":1604,"width":740,"height":179},"7":{"id":"397-9-7","x":5914,"y":1779,"width":740,"height":179},"8":{"id":"397-9-8","x":5914,"y":1955,"width":740,"height":179},"9":{"id":"397-9-9","x":5914,"y":2130,"width":740,"height":179},"10":{"id":"397-9-10","x":5914,"y":2306,"width":740,"height":179},"11":{"id":"397-9-11","x":5914,"y":2481,"width":737,"height":183},"12":{"id":"397-9-12","x":5910,"y":2660,"width":741,"height":176},"13":{"id":"397-9-13","x":5910,"y":2832,"width":741,"height":179},"14":{"id":"397-9-14","x":5910,"y":3008,"width":741,"height":175},"15":{"id":"397-9-15","x":5910,"y":3180,"width":741,"height":175},"16":{"id":"397-9-16","x":5910,"y":3352,"width":741,"height":179},"17":{"id":"397-9-17","x":5910,"y":3527,"width":741,"height":179},"18":{"id":"397-9-18","x":5910,"y":3703,"width":741,"height":179},"19":{"id":"397-9-19","x":5910,"y":3878,"width":741,"height":179},"20":{"id":"397-9-20","x":5910,"y":4054,"width":741,"height":179},"21":{"id":"397-9-21","x":5910,"y":4229,"width":741,"height":179}}}}